{"7106082010001":{"kode_prov":"71","kode_kab":"7106","kode_kec":"710608","kode_kel":"7106082010","kode_tps":"7106082010001","data_tps":{"chart":{"null":null,"100025":10,"100026":185,"100027":42},"images":["https:\/\/sirekap-obj-formc.kpu.go.id\/da89\/pemilu\/ppwp\/71\/06\/08\/20\/10\/7106082010001-20240215-043729--249d91aa-1bbb-4d1c-a6a5-c032fe177de0.jpg","https:\/\/sirekap-obj-formc.kpu.go.id\/da89\/pemilu\/ppwp\/71\/06\/08\/20\/10\/7106082010001-20240215-043910--cb142edb-a3b6-40a6-86f7-ec81e3d03d6a.jpg","https:\/\/sirekap-obj-formc.kpu.go.id\/da89\/pemilu\/ppwp\/71\/06\/08\/20\/10\/7106082010001-20240215-044135--d4a57c49-6d84-4ed4-80c4-fa30db425c28.jpg"],"administrasi":{"suara_sah":237,"suara_total":238,"pemilih_dpt_j":279,"pemilih_dpt_l":147,"pemilih_dpt_p":132,"pengguna_dpt_j":235,"pengguna_dpt_l":117,"pengguna_dpt_p":118,"pengguna_dptb_j":1,"pengguna_dptb_l":1,"pengguna_dptb_p":0,"suara_tidak_sah":1,"pengguna_total_j":238,"pengguna_total_l":118,"pengguna_total_p":120,"pengguna_non_dpt_j":2,"pengguna_non_dpt_l":0,"pengguna_non_dpt_p":2},"psu":null,"ts":"2024-02-15 21:01:18","status_suara":true,"status_adm":true}},"7106082010002":{"kode_prov":"71","kode_kab":"7106","kode_kec":"710608","kode_kel":"7106082010","kode_tps":"7106082010002","data_tps":{"mode":"hhcw","chart":{"null":null,"100025":6,"100026":203,"100027":20},"images":["https:\/\/sirekap-obj-formc.kpu.go.id\/10f8\/pemilu\/ppwp\/71\/06\/08\/20\/10\/7106082010002-20240223-111507--6429b4ec-8274-48dc-93bc-fa1ea6bd4b38.jpg","https:\/\/sirekap-obj-formc.kpu.go.id\/10f8\/pemilu\/ppwp\/71\/06\/08\/20\/10\/7106082010002-20240223-111357--9a8fc99a-e6de-4e72-8957-23d000b37373.jpg","https:\/\/sirekap-obj-formc.kpu.go.id\/10f8\/pemilu\/ppwp\/71\/06\/08\/20\/10\/7106082010002-20240223-111148--b1e325b4-3d47-4281-a521-3f5fb6be6fb1.jpg"],"administrasi":{"suara_sah":229,"suara_total":229,"pemilih_dpt_j":263,"pemilih_dpt_l":136,"pemilih_dpt_p":127,"pengguna_dpt_j":205,"pengguna_dpt_l":100,"pengguna_dpt_p":105,"pengguna_dptb_j":2,"pengguna_dptb_l":0,"pengguna_dptb_p":2,"suara_tidak_sah":0,"pengguna_total_j":229,"pengguna_total_l":109,"pengguna_total_p":120,"pengguna_non_dpt_j":22,"pengguna_non_dpt_l":9,"pengguna_non_dpt_p":13},"psu":null,"ts":"2024-02-24 22:31:28","status_suara":true,"status_adm":true}},"7106082010003":{"kode_prov":"71","kode_kab":"7106","kode_kec":"710608","kode_kel":"7106082010","kode_tps":"7106082010003","data_tps":{"mode":"hhcw","chart":{"null":null,"100025":5,"100026":181,"100027":42},"images":["https:\/\/sirekap-obj-formc.kpu.go.id\/a5dc\/pemilu\/ppwp\/71\/06\/08\/20\/10\/7106082010003-20240218-172444--ec627343-4ca2-4b71-ba2d-0ea04b8b02c5.jpg","https:\/\/sirekap-obj-formc.kpu.go.id\/a5dc\/pemilu\/ppwp\/71\/06\/08\/20\/10\/7106082010003-20240218-172256--34b2a447-c841-4f48-9716-d1e42e35573b.jpg","https:\/\/sirekap-obj-formc.kpu.go.id\/a5dc\/pemilu\/ppwp\/71\/06\/08\/20\/10\/7106082010003-20240218-172332--3266e79f-9da6-4202-85d3-c2a812356654.jpg"],"administrasi":{"suara_sah":228,"suara_total":230,"pemilih_dpt_j":266,"pemilih_dpt_l":121,"pemilih_dpt_p":145,"pengguna_dpt_j":225,"pengguna_dpt_l":99,"pengguna_dpt_p":126,"pengguna_dptb_j":0,"pengguna_dptb_l":0,"pengguna_dptb_p":0,"suara_tidak_sah":2,"pengguna_total_j":230,"pengguna_total_l":102,"pengguna_total_p":128,"pengguna_non_dpt_j":5,"pengguna_non_dpt_l":3,"pengguna_non_dpt_p":2},"psu":null,"ts":"2024-02-19 06:16:00","status_suara":true,"status_adm":true}},"7106082010004":{"kode_prov":"71","kode_kab":"7106","kode_kec":"710608","kode_kel":"7106082010","kode_tps":"7106082010004","data_tps":{"mode":"hhcw","chart":{"null":null,"100025":4,"100026":170,"100027":32},"images":["https:\/\/sirekap-obj-formc.kpu.go.id\/930f\/pemilu\/ppwp\/71\/06\/08\/20\/10\/7106082010004-20240218-173030--0882bbbe-a202-4594-b80c-f672e8d13308.jpg","https:\/\/sirekap-obj-formc.kpu.go.id\/930f\/pemilu\/ppwp\/71\/06\/08\/20\/10\/7106082010004-20240218-173343--7e2dc784-d559-4b7f-8f29-3285cb1034d3.jpg","https:\/\/sirekap-obj-formc.kpu.go.id\/930f\/pemilu\/ppwp\/71\/06\/08\/20\/10\/7106082010004-20240218-173234--5e6840f1-e1f1-4e09-a1ae-ffa1e34dfaf8.jpg"],"administrasi":{"suara_sah":206,"suara_total":208,"pemilih_dpt_j":266,"pemilih_dpt_l":137,"pemilih_dpt_p":129,"pengguna_dpt_j":205,"pengguna_dpt_l":104,"pengguna_dpt_p":101,"pengguna_dptb_j":0,"pengguna_dptb_l":0,"pengguna_dptb_p":0,"suara_tidak_sah":2,"pengguna_total_j":208,"pengguna_total_l":107,"pengguna_total_p":101,"pengguna_non_dpt_j":3,"pengguna_non_dpt_l":3,"pengguna_non_dpt_p":0},"psu":null,"ts":"2024-02-19 06:16:00","status_suara":true,"status_adm":true}},"7106082010005":{"kode_prov":"71","kode_kab":"7106","kode_kec":"710608","kode_kel":"7106082010","kode_tps":"7106082010005","data_tps":{"mode":"hhcw","chart":{"null":null,"100025":3,"100026":176,"100027":41},"images":["https:\/\/sirekap-obj-formc.kpu.go.id\/2259\/pemilu\/ppwp\/71\/06\/08\/20\/10\/7106082010005-20240215-050556--d200d97a-9065-435f-8fc4-b40d62995a65.jpg","https:\/\/sirekap-obj-formc.kpu.go.id\/2259\/pemilu\/ppwp\/71\/06\/08\/20\/10\/7106082010005-20240216-184808--48998cd7-66df-476c-967b-59d3dbee4760.jpg","https:\/\/sirekap-obj-formc.kpu.go.id\/2259\/pemilu\/ppwp\/71\/06\/08\/20\/10\/7106082010005-20240215-023017--0f2408c8-cea3-4e96-9a47-c4db03cea4c3.jpg"],"administrasi":{"suara_sah":220,"suara_total":222,"pemilih_dpt_j":262,"pemilih_dpt_l":129,"pemilih_dpt_p":133,"pengguna_dpt_j":216,"pengguna_dpt_l":104,"pengguna_dpt_p":112,"pengguna_dptb_j":0,"pengguna_dptb_l":0,"pengguna_dptb_p":0,"suara_tidak_sah":2,"pengguna_total_j":222,"pengguna_total_l":108,"pengguna_total_p":114,"pengguna_non_dpt_j":6,"pengguna_non_dpt_l":4,"pengguna_non_dpt_p":2},"psu":null,"ts":"2024-02-16 21:01:00","status_suara":true,"status_adm":true}},"7106082010006":{"kode_prov":"71","kode_kab":"7106","kode_kec":"710608","kode_kel":"7106082010","kode_tps":"7106082010006","data_tps":{"chart":{"null":null,"100025":6,"100026":175,"100027":24},"images":["https:\/\/sirekap-obj-formc.kpu.go.id\/f398\/pemilu\/ppwp\/71\/06\/08\/20\/10\/7106082010006-20240214-232207--1de4cc37-9fe3-4084-85f2-687f475209d4.jpg","https:\/\/sirekap-obj-formc.kpu.go.id\/f398\/pemilu\/ppwp\/71\/06\/08\/20\/10\/7106082010006-20240214-232215--e22caf31-bd50-41f4-9058-2fbdc8de6888.jpg","https:\/\/sirekap-obj-formc.kpu.go.id\/f398\/pemilu\/ppwp\/71\/06\/08\/20\/10\/7106082010006-20240214-232223--33a45298-86f1-438c-b911-869082e5fc07.jpg"],"administrasi":{"suara_sah":205,"suara_total":206,"pemilih_dpt_j":272,"pemilih_dpt_l":130,"pemilih_dpt_p":142,"pengguna_dpt_j":202,"pengguna_dpt_l":86,"pengguna_dpt_p":116,"pengguna_dptb_j":0,"pengguna_dptb_l":0,"pengguna_dptb_p":0,"suara_tidak_sah":1,"pengguna_total_j":206,"pengguna_total_l":88,"pengguna_total_p":118,"pengguna_non_dpt_j":4,"pengguna_non_dpt_l":2,"pengguna_non_dpt_p":2},"psu":null,"ts":"2024-02-15 22:30:27","status_suara":true,"status_adm":true}},"7106082010007":{"kode_prov":"71","kode_kab":"7106","kode_kec":"710608","kode_kel":"7106082010","kode_tps":"7106082010007","data_tps":{"chart":{"null":null,"100025":11,"100026":148,"100027":32},"images":["https:\/\/sirekap-obj-formc.kpu.go.id\/eef0\/pemilu\/ppwp\/71\/06\/08\/20\/10\/7106082010007-20240215-054441--2f66cb17-f8b8-40d2-a98b-985401bb08c9.jpg","https:\/\/sirekap-obj-formc.kpu.go.id\/eef0\/pemilu\/ppwp\/71\/06\/08\/20\/10\/7106082010007-20240215-053801--46cb885f-9ad7-4d68-9285-769364be5972.jpg","https:\/\/sirekap-obj-formc.kpu.go.id\/eef0\/pemilu\/ppwp\/71\/06\/08\/20\/10\/7106082010007-20240215-053841--32158b9c-52a5-41f5-9f8b-23cf3139f966.jpg"],"administrasi":{"suara_sah":191,"suara_total":191,"pemilih_dpt_j":267,"pemilih_dpt_l":125,"pemilih_dpt_p":142,"pengguna_dpt_j":188,"pengguna_dpt_l":84,"pengguna_dpt_p":104,"pengguna_dptb_j":3,"pengguna_dptb_l":0,"pengguna_dptb_p":3,"suara_tidak_sah":0,"pengguna_total_j":191,"pengguna_total_l":84,"pengguna_total_p":107,"pengguna_non_dpt_j":0,"pengguna_non_dpt_l":0,"pengguna_non_dpt_p":0},"psu":null,"ts":"2024-02-15 20:30:46","status_suara":true,"status_adm":true}},"7106082010008":{"kode_prov":"71","kode_kab":"7106","kode_kec":"710608","kode_kel":"7106082010","kode_tps":"7106082010008","data_tps":{"chart":{"null":null,"100025":2,"100026":66,"100027":12},"images":["https:\/\/sirekap-obj-formc.kpu.go.id\/dacc\/pemilu\/ppwp\/71\/06\/08\/20\/10\/7106082010008-20240214-210506--912c2f04-ad9d-48ea-8448-4891bc35473e.jpg","https:\/\/sirekap-obj-formc.kpu.go.id\/dacc\/pemilu\/ppwp\/71\/06\/08\/20\/10\/7106082010008-20240214-210732--fab23fa0-f079-4657-b5ae-288666dfbeb8.jpg","https:\/\/sirekap-obj-formc.kpu.go.id\/dacc\/pemilu\/ppwp\/71\/06\/08\/20\/10\/7106082010008-20240215-015720--5fe6cdbf-3466-42fe-89b4-bb219f0aae6d.jpg"],"administrasi":null,"psu":null,"ts":"2024-02-15 02:10:27","status_suara":true,"status_adm":false}},"7106082006001":{"kode_prov":"71","kode_kab":"7106","kode_kec":"710608","kode_kel":"7106082006","kode_tps":"7106082006001","data_tps":{"mode":"hhcw","chart":{"null":null,"100025":1,"100026":176,"100027":74},"images":["https:\/\/sirekap-obj-formc.kpu.go.id\/4210\/pemilu\/ppwp\/71\/06\/08\/20\/06\/7106082006001-20240217-095738--c1de3f65-c9ec-40e7-bac6-b5e0e0f71618.jpg","https:\/\/sirekap-obj-formc.kpu.go.id\/4210\/pemilu\/ppwp\/71\/06\/08\/20\/06\/7106082006001-20240217-095757--6efb0057-2a61-4e77-9c3d-925af9df063b.jpg","https:\/\/sirekap-obj-formc.kpu.go.id\/4210\/pemilu\/ppwp\/71\/06\/08\/20\/06\/7106082006001-20240217-095815--96e85e2f-6bfc-4162-8489-a7e2525605bc.jpg"],"administrasi":{"suara_sah":251,"suara_total":253,"pemilih_dpt_j":292,"pemilih_dpt_l":141,"pemilih_dpt_p":151,"pengguna_dpt_j":251,"pengguna_dpt_l":118,"pengguna_dpt_p":133,"pengguna_dptb_j":0,"pengguna_dptb_l":0,"pengguna_dptb_p":0,"suara_tidak_sah":2,"pengguna_total_j":253,"pengguna_total_l":119,"pengguna_total_p":134,"pengguna_non_dpt_j":2,"pengguna_non_dpt_l":1,"pengguna_non_dpt_p":1},"psu":null,"ts":"2024-02-17 10:30:03","status_suara":true,"status_adm":true}},"7106082006002":{"kode_prov":"71","kode_kab":"7106","kode_kec":"710608","kode_kel":"7106082006","kode_tps":"7106082006002","data_tps":{"mode":"hhcw","chart":{"null":null,"100025":1,"100026":201,"100027":56},"images":["https:\/\/sirekap-obj-formc.kpu.go.id\/2fe2\/pemilu\/ppwp\/71\/06\/08\/20\/06\/7106082006002-20240217-131033--8b2843ab-4867-4d5c-867c-ec39474afb14.jpg","https:\/\/sirekap-obj-formc.kpu.go.id\/2fe2\/pemilu\/ppwp\/71\/06\/08\/20\/06\/7106082006002-20240217-130900--ccff9d90-9e4a-4e43-bd70-830cef812882.jpg","https:\/\/sirekap-obj-formc.kpu.go.id\/2fe2\/pemilu\/ppwp\/71\/06\/08\/20\/06\/7106082006002-20240217-131346--84f8d2c2-c4fb-47ef-93b3-d69fa9748b0e.jpg"],"administrasi":{"suara_sah":258,"suara_total":259,"pemilih_dpt_j":295,"pemilih_dpt_l":148,"pemilih_dpt_p":147,"pengguna_dpt_j":255,"pengguna_dpt_l":125,"pengguna_dpt_p":130,"pengguna_dptb_j":0,"pengguna_dptb_l":0,"pengguna_dptb_p":0,"suara_tidak_sah":1,"pengguna_total_j":259,"pengguna_total_l":126,"pengguna_total_p":133,"pengguna_non_dpt_j":4,"pengguna_non_dpt_l":1,"pengguna_non_dpt_p":3},"psu":null,"ts":"2024-02-20 12:00:00","status_suara":true,"status_adm":true}},"7106082003001":{"kode_prov":"71","kode_kab":"7106","kode_kec":"710608","kode_kel":"7106082003","kode_tps":"7106082003001","data_tps":{"mode":"hhcw","chart":{"null":null,"100025":18,"100026":146,"100027":43},"images":["https:\/\/sirekap-obj-formc.kpu.go.id\/8abd\/pemilu\/ppwp\/71\/06\/08\/20\/03\/7106082003001-20240216-141930--78eeb23b-21b1-44a6-a154-1c48a0c3bd0b.jpg","https:\/\/sirekap-obj-formc.kpu.go.id\/8abd\/pemilu\/ppwp\/71\/06\/08\/20\/03\/7106082003001-20240216-141932--107e2cca-db16-46eb-8505-f46df818af7b.jpg","https:\/\/sirekap-obj-formc.kpu.go.id\/8abd\/pemilu\/ppwp\/71\/06\/08\/20\/03\/7106082003001-20240216-141931--ea16d627-45fd-4136-9dc1-eecd6d389e95.jpg"],"administrasi":{"suara_sah":207,"suara_total":209,"pemilih_dpt_j":229,"pemilih_dpt_l":105,"pemilih_dpt_p":124,"pengguna_dpt_j":200,"pengguna_dpt_l":87,"pengguna_dpt_p":113,"pengguna_dptb_j":8,"pengguna_dptb_l":4,"pengguna_dptb_p":4,"suara_tidak_sah":2,"pengguna_total_j":209,"pengguna_total_l":92,"pengguna_total_p":117,"pengguna_non_dpt_j":1,"pengguna_non_dpt_l":1,"pengguna_non_dpt_p":0},"psu":null,"ts":"2024-02-16 16:25:10","status_suara":true,"status_adm":true}},"7106082003002":{"kode_prov":"71","kode_kab":"7106","kode_kec":"710608","kode_kel":"7106082003","kode_tps":"7106082003002","data_tps":{"chart":{"null":null,"100025":5,"100026":188,"100027":36},"images":["https:\/\/sirekap-obj-formc.kpu.go.id\/99c2\/pemilu\/ppwp\/71\/06\/08\/20\/03\/7106082003002-20240214-215552--845bf5ce-0e12-43a6-9e24-da42a7590797.jpg","https:\/\/sirekap-obj-formc.kpu.go.id\/99c2\/pemilu\/ppwp\/71\/06\/08\/20\/03\/7106082003002-20240215-050501--5718ffee-2768-4201-a523-dde5e335c77a.jpg","https:\/\/sirekap-obj-formc.kpu.go.id\/99c2\/pemilu\/ppwp\/71\/06\/08\/20\/03\/7106082003002-20240214-215647--c75d3034-ab26-439f-a506-882117b2a168.jpg"],"administrasi":{"suara_sah":229,"suara_total":229,"pemilih_dpt_j":258,"pemilih_dpt_l":122,"pemilih_dpt_p":136,"pengguna_dpt_j":217,"pengguna_dpt_l":97,"pengguna_dpt_p":120,"pengguna_dptb_j":8,"pengguna_dptb_l":5,"pengguna_dptb_p":3,"suara_tidak_sah":0,"pengguna_total_j":229,"pengguna_total_l":104,"pengguna_total_p":125,"pengguna_non_dpt_j":4,"pengguna_non_dpt_l":2,"pengguna_non_dpt_p":2},"psu":null,"ts":"2024-02-15 20:00:44","status_suara":true,"status_adm":true}},"7106082003003":{"kode_prov":"71","kode_kab":"7106","kode_kec":"710608","kode_kel":"7106082003","kode_tps":"7106082003003","data_tps":{"chart":{"null":null,"100025":8,"100026":181,"100027":28},"images":["https:\/\/sirekap-obj-formc.kpu.go.id\/352b\/pemilu\/ppwp\/71\/06\/08\/20\/03\/7106082003003-20240214-160140--c428787b-7610-4f89-943b-de84fe1815d8.jpg","https:\/\/sirekap-obj-formc.kpu.go.id\/352b\/pemilu\/ppwp\/71\/06\/08\/20\/03\/7106082003003-20240215-091448--ea63922b-89ec-4952-ac23-93d239c04107.jpg","https:\/\/sirekap-obj-formc.kpu.go.id\/352b\/pemilu\/ppwp\/71\/06\/08\/20\/03\/7106082003003-20240214-141642--d6583179-a0f0-44d8-9349-115b56d4940b.jpg"],"administrasi":{"suara_sah":217,"suara_total":221,"pemilih_dpt_j":251,"pemilih_dpt_l":136,"pemilih_dpt_p":115,"pengguna_dpt_j":215,"pengguna_dpt_l":111,"pengguna_dpt_p":104,"pengguna_dptb_j":3,"pengguna_dptb_l":2,"pengguna_dptb_p":1,"suara_tidak_sah":4,"pengguna_total_j":221,"pengguna_total_l":114,"pengguna_total_p":107,"pengguna_non_dpt_j":3,"pengguna_non_dpt_l":1,"pengguna_non_dpt_p":2},"psu":null,"ts":"2024-02-15 17:00:25","status_suara":true,"status_adm":true}},"7106082003004":{"kode_prov":"71","kode_kab":"7106","kode_kec":"710608","kode_kel":"7106082003","kode_tps":"7106082003004","data_tps":{"chart":{"null":null,"100025":2,"100026":185,"100027":35},"images":["https:\/\/sirekap-obj-formc.kpu.go.id\/dd21\/pemilu\/ppwp\/71\/06\/08\/20\/03\/7106082003004-20240214-211234--0ffe9089-6185-4690-8e7f-c1bec96c1f18.jpg","https:\/\/sirekap-obj-formc.kpu.go.id\/dd21\/pemilu\/ppwp\/71\/06\/08\/20\/03\/7106082003004-20240214-210939--986a19f2-791b-447a-ba0b-8b350fde997e.jpg","https:\/\/sirekap-obj-formc.kpu.go.id\/dd21\/pemilu\/ppwp\/71\/06\/08\/20\/03\/7106082003004-20240214-210954--1a8a76af-7624-45b9-a42f-b089ae6ef19e.jpg"],"administrasi":{"suara_sah":222,"suara_total":224,"pemilih_dpt_j":248,"pemilih_dpt_l":121,"pemilih_dpt_p":127,"pengguna_dpt_j":221,"pengguna_dpt_l":105,"pengguna_dpt_p":116,"pengguna_dptb_j":2,"pengguna_dptb_l":1,"pengguna_dptb_p":1,"suara_tidak_sah":2,"pengguna_total_j":224,"pengguna_total_l":107,"pengguna_total_p":117,"pengguna_non_dpt_j":1,"pengguna_non_dpt_l":1,"pengguna_non_dpt_p":0},"psu":null,"ts":"2024-02-15 00:41:44","status_suara":true,"status_adm":true}},"7106082003005":{"kode_prov":"71","kode_kab":"7106","kode_kec":"710608","kode_kel":"7106082003","kode_tps":"7106082003005","data_tps":{"chart":{"null":null,"100025":8,"100026":212,"100027":30},"images":["https:\/\/sirekap-obj-formc.kpu.go.id\/ae79\/pemilu\/ppwp\/71\/06\/08\/20\/03\/7106082003005-20240214-155022--4248b7f1-3c4d-464f-a0ea-1393946f3348.jpg","https:\/\/sirekap-obj-formc.kpu.go.id\/ae79\/pemilu\/ppwp\/71\/06\/08\/20\/03\/7106082003005-20240214-155152--8f16b6d6-5bb5-4293-9250-9520ff7384ca.jpg","https:\/\/sirekap-obj-formc.kpu.go.id\/ae79\/pemilu\/ppwp\/71\/06\/08\/20\/03\/7106082003005-20240214-155228--0a2d10cc-a7fe-469f-89fc-aed0681b4b65.jpg"],"administrasi":{"suara_sah":250,"suara_total":251,"pemilih_dpt_j":273,"pemilih_dpt_l":128,"pemilih_dpt_p":145,"pengguna_dpt_j":243,"pengguna_dpt_l":113,"pengguna_dpt_p":130,"pengguna_dptb_j":1,"pengguna_dptb_l":0,"pengguna_dptb_p":1,"suara_tidak_sah":1,"pengguna_total_j":251,"pengguna_total_l":118,"pengguna_total_p":133,"pengguna_non_dpt_j":7,"pengguna_non_dpt_l":5,"pengguna_non_dpt_p":2},"psu":null,"ts":"2024-02-15 19:00:26","status_suara":true,"status_adm":true}},"7106082003006":{"kode_prov":"71","kode_kab":"7106","kode_kec":"710608","kode_kel":"7106082003","kode_tps":"7106082003006","data_tps":{"chart":{"null":null,"100025":1,"100026":187,"100027":43},"images":["https:\/\/sirekap-obj-formc.kpu.go.id\/ab95\/pemilu\/ppwp\/71\/06\/08\/20\/03\/7106082003006-20240214-141250--10000055-4b91-4cf3-9cbc-d80f4ce710e0.jpg","https:\/\/sirekap-obj-formc.kpu.go.id\/ab95\/pemilu\/ppwp\/71\/06\/08\/20\/03\/7106082003006-20240214-141538--08a04c6f-78fd-4a01-ac59-72a080a2ded9.jpg","https:\/\/sirekap-obj-formc.kpu.go.id\/ab95\/pemilu\/ppwp\/71\/06\/08\/20\/03\/7106082003006-20240215-084633--a848d230-aeb7-4687-8937-b456fd712fa1.jpg"],"administrasi":{"suara_sah":231,"suara_total":232,"pemilih_dpt_j":253,"pemilih_dpt_l":130,"pemilih_dpt_p":123,"pengguna_dpt_j":227,"pengguna_dpt_l":112,"pengguna_dpt_p":115,"pengguna_dptb_j":4,"pengguna_dptb_l":1,"pengguna_dptb_p":3,"suara_tidak_sah":1,"pengguna_total_j":232,"pengguna_total_l":114,"pengguna_total_p":118,"pengguna_non_dpt_j":1,"pengguna_non_dpt_l":1,"pengguna_non_dpt_p":0},"psu":null,"ts":"2024-02-16 12:51:22","status_suara":true,"status_adm":true}},"7106082009001":{"kode_prov":"71","kode_kab":"7106","kode_kec":"710608","kode_kel":"7106082009","kode_tps":"7106082009001","data_tps":{"mode":"hhcw","chart":{"null":null,"100025":4,"100026":156,"100027":64},"images":["https:\/\/sirekap-obj-formc.kpu.go.id\/ade4\/pemilu\/ppwp\/71\/06\/08\/20\/09\/7106082009001-20240217-152920--8875b7f9-c09e-42ab-839f-74fb4ee83a24.jpg","https:\/\/sirekap-obj-formc.kpu.go.id\/ade4\/pemilu\/ppwp\/71\/06\/08\/20\/09\/7106082009001-20240223-152737--041884b2-00b6-44a5-84af-64fb43d06e0d.jpg","https:\/\/sirekap-obj-formc.kpu.go.id\/ade4\/pemilu\/ppwp\/71\/06\/08\/20\/09\/7106082009001-20240217-153215--665a515c-7d3b-457c-91de-08c9be52912b.jpg"],"administrasi":{"suara_sah":224,"suara_total":224,"pemilih_dpt_j":280,"pemilih_dpt_l":132,"pemilih_dpt_p":148,"pengguna_dpt_j":213,"pengguna_dpt_l":98,"pengguna_dpt_p":115,"pengguna_dptb_j":2,"pengguna_dptb_l":1,"pengguna_dptb_p":1,"suara_tidak_sah":0,"pengguna_total_j":224,"pengguna_total_l":101,"pengguna_total_p":123,"pengguna_non_dpt_j":9,"pengguna_non_dpt_l":2,"pengguna_non_dpt_p":7},"psu":null,"ts":"2024-02-24 22:31:28","status_suara":true,"status_adm":true}},"7106082009002":{"kode_prov":"71","kode_kab":"7106","kode_kec":"710608","kode_kel":"7106082009","kode_tps":"7106082009002","data_tps":{"chart":{"null":null,"100025":4,"100026":216,"100027":32},"images":["https:\/\/sirekap-obj-formc.kpu.go.id\/7d84\/pemilu\/ppwp\/71\/06\/08\/20\/09\/7106082009002-20240215-063052--dc5c99e5-58c3-41c5-b715-0891267c686c.jpg","https:\/\/sirekap-obj-formc.kpu.go.id\/7d84\/pemilu\/ppwp\/71\/06\/08\/20\/09\/7106082009002-20240215-063415--1d891fff-d357-495f-ae42-f77094ccd7fd.jpg","https:\/\/sirekap-obj-formc.kpu.go.id\/7d84\/pemilu\/ppwp\/71\/06\/08\/20\/09\/7106082009002-20240215-054950--3f55cc39-a3cf-4e63-8d90-6655c3983b57.jpg"],"administrasi":{"suara_sah":252,"suara_total":254,"pemilih_dpt_j":281,"pemilih_dpt_l":149,"pemilih_dpt_p":132,"pengguna_dpt_j":247,"pengguna_dpt_l":128,"pengguna_dpt_p":119,"pengguna_dptb_j":0,"pengguna_dptb_l":0,"pengguna_dptb_p":0,"suara_tidak_sah":2,"pengguna_total_j":254,"pengguna_total_l":0,"pengguna_total_p":0,"pengguna_non_dpt_j":7,"pengguna_non_dpt_l":2,"pengguna_non_dpt_p":5},"psu":null,"ts":"2024-02-15 21:01:18","status_suara":true,"status_adm":true}},"7106082009003":{"kode_prov":"71","kode_kab":"7106","kode_kec":"710608","kode_kel":"7106082009","kode_tps":"7106082009003","data_tps":{"mode":"hhcw","chart":{"null":null,"100025":9,"100026":150,"100027":35},"images":["https:\/\/sirekap-obj-formc.kpu.go.id\/ea78\/pemilu\/ppwp\/71\/06\/08\/20\/09\/7106082009003-20240223-145335--705b7a55-3f6d-4956-a8db-11a2c2039ead.jpg","https:\/\/sirekap-obj-formc.kpu.go.id\/ea78\/pemilu\/ppwp\/71\/06\/08\/20\/09\/7106082009003-20240223-095342--5d140ce6-4fa4-4bbe-9c93-2a9ef2a1ef91.jpg","https:\/\/sirekap-obj-formc.kpu.go.id\/ea78\/pemilu\/ppwp\/71\/06\/08\/20\/09\/7106082009003-20240223-095559--6ad1811d-939e-4d5a-bd28-0e7cf18680c5.jpg"],"administrasi":{"suara_sah":194,"suara_total":199,"pemilih_dpt_j":267,"pemilih_dpt_l":110,"pemilih_dpt_p":157,"pengguna_dpt_j":194,"pengguna_dpt_l":99,"pengguna_dpt_p":95,"pengguna_dptb_j":2,"pengguna_dptb_l":1,"pengguna_dptb_p":1,"suara_tidak_sah":5,"pengguna_total_j":199,"pengguna_total_l":101,"pengguna_total_p":98,"pengguna_non_dpt_j":3,"pengguna_non_dpt_l":1,"pengguna_non_dpt_p":2},"psu":null,"ts":"2024-02-24 22:31:28","status_suara":true,"status_adm":true}},"7106082009004":{"kode_prov":"71","kode_kab":"7106","kode_kec":"710608","kode_kel":"7106082009","kode_tps":"7106082009004","data_tps":{"mode":"hhcw","chart":{"null":null,"100025":14,"100026":149,"100027":32},"images":["https:\/\/sirekap-obj-formc.kpu.go.id\/cf76\/pemilu\/ppwp\/71\/06\/08\/20\/09\/7106082009004-20240214-221453--50576d02-1f19-4321-97f3-a92422c1869d.jpg","https:\/\/sirekap-obj-formc.kpu.go.id\/cf76\/pemilu\/ppwp\/71\/06\/08\/20\/09\/7106082009004-20240215-021418--d08e158f-e466-4caa-8a69-03afceec7913.jpg","https:\/\/sirekap-obj-formc.kpu.go.id\/cf76\/pemilu\/ppwp\/71\/06\/08\/20\/09\/7106082009004-20240215-021852--af47dce9-5320-4051-bb51-8c4de6d2f416.jpg"],"administrasi":{"suara_sah":195,"suara_total":198,"pemilih_dpt_j":289,"pemilih_dpt_l":144,"pemilih_dpt_p":145,"pengguna_dpt_j":195,"pengguna_dpt_l":92,"pengguna_dpt_p":103,"pengguna_dptb_j":0,"pengguna_dptb_l":0,"pengguna_dptb_p":0,"suara_tidak_sah":3,"pengguna_total_j":198,"pengguna_total_l":93,"pengguna_total_p":105,"pengguna_non_dpt_j":3,"pengguna_non_dpt_l":1,"pengguna_non_dpt_p":2},"psu":null,"ts":"2024-02-16 23:45:47","status_suara":true,"status_adm":true}},"7106082009005":{"kode_prov":"71","kode_kab":"7106","kode_kec":"710608","kode_kel":"7106082009","kode_tps":"7106082009005","data_tps":{"mode":"hhcw","chart":{"null":null,"100025":11,"100026":177,"100027":34},"images":["https:\/\/sirekap-obj-formc.kpu.go.id\/f669\/pemilu\/ppwp\/71\/06\/08\/20\/09\/7106082009005-20240218-174915--9a541fee-42a3-41d0-861e-d5f5f07f7103.jpg","https:\/\/sirekap-obj-formc.kpu.go.id\/f669\/pemilu\/ppwp\/71\/06\/08\/20\/09\/7106082009005-20240218-175148--28628b32-9c69-4911-b104-396844bda388.jpg","https:\/\/sirekap-obj-formc.kpu.go.id\/f669\/pemilu\/ppwp\/71\/06\/08\/20\/09\/7106082009005-20240218-175046--74f44189-d2d3-42d4-b824-c3dd15492e8b.jpg"],"administrasi":{"suara_sah":222,"suara_total":224,"pemilih_dpt_j":275,"pemilih_dpt_l":131,"pemilih_dpt_p":144,"pengguna_dpt_j":220,"pengguna_dpt_l":101,"pengguna_dpt_p":119,"pengguna_dptb_j":2,"pengguna_dptb_l":1,"pengguna_dptb_p":1,"suara_tidak_sah":2,"pengguna_total_j":224,"pengguna_total_l":103,"pengguna_total_p":121,"pengguna_non_dpt_j":2,"pengguna_non_dpt_l":1,"pengguna_non_dpt_p":1},"psu":null,"ts":"2024-02-19 06:16:00","status_suara":true,"status_adm":true}},"7106082009006":{"kode_prov":"71","kode_kab":"7106","kode_kec":"710608","kode_kel":"7106082009","kode_tps":"7106082009006","data_tps":{"mode":"hhcw","chart":{"null":null,"100025":12,"100026":170,"100027":33},"images":["https:\/\/sirekap-obj-formc.kpu.go.id\/f462\/pemilu\/ppwp\/71\/06\/08\/20\/09\/7106082009006-20240217-154715--ceebf34d-03dd-4179-a882-ed0a88636e68.jpg","https:\/\/sirekap-obj-formc.kpu.go.id\/f462\/pemilu\/ppwp\/71\/06\/08\/20\/09\/7106082009006-20240217-154434--b87f2a96-9cd1-41df-901b-d42827bfafab.jpg","https:\/\/sirekap-obj-formc.kpu.go.id\/f462\/pemilu\/ppwp\/71\/06\/08\/20\/09\/7106082009006-20240217-154556--adbedfe3-b53d-401c-8843-b8cbd1ae937e.jpg"],"administrasi":{"suara_sah":215,"suara_total":218,"pemilih_dpt_j":277,"pemilih_dpt_l":136,"pemilih_dpt_p":141,"pengguna_dpt_j":216,"pengguna_dpt_l":101,"pengguna_dpt_p":115,"pengguna_dptb_j":2,"pengguna_dptb_l":1,"pengguna_dptb_p":1,"suara_tidak_sah":3,"pengguna_total_j":218,"pengguna_total_l":102,"pengguna_total_p":116,"pengguna_non_dpt_j":0,"pengguna_non_dpt_l":0,"pengguna_non_dpt_p":0},"psu":null,"ts":"2024-02-19 06:16:00","status_suara":true,"status_adm":true}},"7106082009007":{"kode_prov":"71","kode_kab":"7106","kode_kec":"710608","kode_kel":"7106082009","kode_tps":"7106082009007","data_tps":{"mode":"hhcw","chart":{"null":null,"100025":6,"100026":153,"100027":49},"images":["https:\/\/sirekap-obj-formc.kpu.go.id\/5223\/pemilu\/ppwp\/71\/06\/08\/20\/09\/7106082009007-20240223-094144--ace3e7bb-37de-4633-9543-96874c6b70c4.jpg","https:\/\/sirekap-obj-formc.kpu.go.id\/5223\/pemilu\/ppwp\/71\/06\/08\/20\/09\/7106082009007-20240223-094308--f8909a29-2282-4cc9-a83e-0583fdc84c00.jpg","https:\/\/sirekap-obj-formc.kpu.go.id\/5223\/pemilu\/ppwp\/71\/06\/08\/20\/09\/7106082009007-20240223-094423--5baffa41-d9cc-496a-9903-60f14f330bf2.jpg"],"administrasi":{"suara_sah":208,"suara_total":208,"pemilih_dpt_j":283,"pemilih_dpt_l":133,"pemilih_dpt_p":148,"pengguna_dpt_j":204,"pengguna_dpt_l":89,"pengguna_dpt_p":115,"pengguna_dptb_j":0,"pengguna_dptb_l":0,"pengguna_dptb_p":0,"suara_tidak_sah":0,"pengguna_total_j":208,"pengguna_total_l":93,"pengguna_total_p":115,"pengguna_non_dpt_j":4,"pengguna_non_dpt_l":4,"pengguna_non_dpt_p":0},"psu":null,"ts":"2024-02-24 22:31:28","status_suara":true,"status_adm":true}},"7106082009008":{"kode_prov":"71","kode_kab":"7106","kode_kec":"710608","kode_kel":"7106082009","kode_tps":"7106082009008","data_tps":{"chart":{"null":null,"100025":1,"100026":196,"100027":44},"images":["https:\/\/sirekap-obj-formc.kpu.go.id\/2bf4\/pemilu\/ppwp\/71\/06\/08\/20\/09\/7106082009008-20240214-201232--e1073df7-ba5e-4a04-b055-7299029021c5.jpg","https:\/\/sirekap-obj-formc.kpu.go.id\/2bf4\/pemilu\/ppwp\/71\/06\/08\/20\/09\/7106082009008-20240214-201717--4d1c4c76-4ff7-48e2-b7af-1eed8903429c.jpg","https:\/\/sirekap-obj-formc.kpu.go.id\/2bf4\/pemilu\/ppwp\/71\/06\/08\/20\/09\/7106082009008-20240214-202114--faed3c34-b8cd-415d-9bb9-87791eff1096.jpg"],"administrasi":{"suara_sah":241,"suara_total":241,"pemilih_dpt_j":294,"pemilih_dpt_l":136,"pemilih_dpt_p":158,"pengguna_dpt_j":236,"pengguna_dpt_l":108,"pengguna_dpt_p":128,"pengguna_dptb_j":0,"pengguna_dptb_l":0,"pengguna_dptb_p":0,"suara_tidak_sah":0,"pengguna_total_j":241,"pengguna_total_l":111,"pengguna_total_p":130,"pengguna_non_dpt_j":5,"pengguna_non_dpt_l":3,"pengguna_non_dpt_p":2},"psu":null,"ts":"2024-02-15 12:00:28","status_suara":true,"status_adm":true}},"7106082004001":{"kode_prov":"71","kode_kab":"7106","kode_kec":"710608","kode_kel":"7106082004","kode_tps":"7106082004001","data_tps":{"mode":"hhcw","chart":{"null":null,"100025":2,"100026":195,"100027":57},"images":["https:\/\/sirekap-obj-formc.kpu.go.id\/5bcd\/pemilu\/ppwp\/71\/06\/08\/20\/04\/7106082004001-20240225-223929--f286fab5-3d2a-43b7-be13-c30216a8b97e.jpg","https:\/\/sirekap-obj-formc.kpu.go.id\/5bcd\/pemilu\/ppwp\/71\/06\/08\/20\/04\/7106082004001-20240225-223801--3729c1b4-26b2-4deb-9e7e-4a6491f5a61b.jpg","https:\/\/sirekap-obj-formc.kpu.go.id\/5bcd\/pemilu\/ppwp\/71\/06\/08\/20\/04\/7106082004001-20240225-223845--a4856898-5ae5-457a-918f-4c8a295c07d3.jpg"],"administrasi":null,"psu":null,"ts":"2024-02-26 00:00:00","status_suara":true,"status_adm":false}},"7106082004002":{"kode_prov":"71","kode_kab":"7106","kode_kec":"710608","kode_kel":"7106082004","kode_tps":"7106082004002","data_tps":{"chart":{"null":null,"100025":9,"100026":155,"100027":62},"images":["https:\/\/sirekap-obj-formc.kpu.go.id\/1934\/pemilu\/ppwp\/71\/06\/08\/20\/04\/7106082004002-20240214-231343--f9342b95-c3b7-4050-be9a-6a49449da2e0.jpg","https:\/\/sirekap-obj-formc.kpu.go.id\/1934\/pemilu\/ppwp\/71\/06\/08\/20\/04\/7106082004002-20240214-231236--7d4bcb6e-bf0f-4fb6-8f20-8c8ba0fac3aa.jpg","https:\/\/sirekap-obj-formc.kpu.go.id\/1934\/pemilu\/ppwp\/71\/06\/08\/20\/04\/7106082004002-20240214-231432--d496beb0-9de2-45c9-86db-eece0d02ba8d.jpg"],"administrasi":{"suara_sah":226,"suara_total":226,"pemilih_dpt_j":261,"pemilih_dpt_l":133,"pemilih_dpt_p":128,"pengguna_dpt_j":217,"pengguna_dpt_l":107,"pengguna_dpt_p":110,"pengguna_dptb_j":0,"pengguna_dptb_l":0,"pengguna_dptb_p":0,"suara_tidak_sah":0,"pengguna_total_j":226,"pengguna_total_l":112,"pengguna_total_p":114,"pengguna_non_dpt_j":9,"pengguna_non_dpt_l":5,"pengguna_non_dpt_p":4},"psu":null,"ts":"2024-02-15 19:00:26","status_suara":true,"status_adm":true}},"7106082004003":{"kode_prov":"71","kode_kab":"7106","kode_kec":"710608","kode_kel":"7106082004","kode_tps":"7106082004003","data_tps":{"chart":{"null":null,"100025":15,"100026":163,"100027":63},"images":["https:\/\/sirekap-obj-formc.kpu.go.id\/b2e0\/pemilu\/ppwp\/71\/06\/08\/20\/04\/7106082004003-20240214-224955--ec1e7a66-c93b-4b97-9915-31310c1764ec.jpg","https:\/\/sirekap-obj-formc.kpu.go.id\/b2e0\/pemilu\/ppwp\/71\/06\/08\/20\/04\/7106082004003-20240214-225347--41a0db68-a55d-48d7-a103-1f78b51a4bb6.jpg","https:\/\/sirekap-obj-formc.kpu.go.id\/b2e0\/pemilu\/ppwp\/71\/06\/08\/20\/04\/7106082004003-20240214-205414--8d09725d-d6bf-48b1-8ea7-626d6486b67a.jpg"],"administrasi":{"suara_sah":241,"suara_total":242,"pemilih_dpt_j":266,"pemilih_dpt_l":129,"pemilih_dpt_p":137,"pengguna_dpt_j":236,"pengguna_dpt_l":116,"pengguna_dpt_p":120,"pengguna_dptb_j":0,"pengguna_dptb_l":0,"pengguna_dptb_p":0,"suara_tidak_sah":1,"pengguna_total_j":242,"pengguna_total_l":118,"pengguna_total_p":124,"pengguna_non_dpt_j":6,"pengguna_non_dpt_l":2,"pengguna_non_dpt_p":4},"psu":null,"ts":"2024-02-15 23:29:50","status_suara":true,"status_adm":true}},"7106082004004":{"kode_prov":"71","kode_kab":"7106","kode_kec":"710608","kode_kel":"7106082004","kode_tps":"7106082004004","data_tps":{"chart":{"null":null,"100025":12,"100026":154,"100027":47},"images":["https:\/\/sirekap-obj-formc.kpu.go.id\/0bff\/pemilu\/ppwp\/71\/06\/08\/20\/04\/7106082004004-20240215-033833--49df643b-e8fb-417d-afd5-259077fd9638.jpg","https:\/\/sirekap-obj-formc.kpu.go.id\/0bff\/pemilu\/ppwp\/71\/06\/08\/20\/04\/7106082004004-20240215-040228--0a3b2ae1-6de4-4796-ae17-be34ea4f5df4.jpg","https:\/\/sirekap-obj-formc.kpu.go.id\/0bff\/pemilu\/ppwp\/71\/06\/08\/20\/04\/7106082004004-20240215-040258--1ded274f-2ea7-4ea9-82c8-37a89b3be2bd.jpg"],"administrasi":{"suara_sah":213,"suara_total":214,"pemilih_dpt_j":262,"pemilih_dpt_l":117,"pemilih_dpt_p":145,"pengguna_dpt_j":211,"pengguna_dpt_l":96,"pengguna_dpt_p":115,"pengguna_dptb_j":3,"pengguna_dptb_l":2,"pengguna_dptb_p":1,"suara_tidak_sah":1,"pengguna_total_j":216,"pengguna_total_l":98,"pengguna_total_p":116,"pengguna_non_dpt_j":0,"pengguna_non_dpt_l":0,"pengguna_non_dpt_p":0},"psu":null,"ts":"2024-02-15 20:00:44","status_suara":true,"status_adm":true}},"7106082004005":{"kode_prov":"71","kode_kab":"7106","kode_kec":"710608","kode_kel":"7106082004","kode_tps":"7106082004005","data_tps":{"chart":{"null":null,"100025":16,"100026":161,"100027":48},"images":["https:\/\/sirekap-obj-formc.kpu.go.id\/a12e\/pemilu\/ppwp\/71\/06\/08\/20\/04\/7106082004005-20240216-095054--868d9897-9bfb-4077-b992-824a9b77d660.jpg","https:\/\/sirekap-obj-formc.kpu.go.id\/a12e\/pemilu\/ppwp\/71\/06\/08\/20\/04\/7106082004005-20240216-095056--ab432eb0-26d0-4e44-b1ed-72d26cd99027.jpg","https:\/\/sirekap-obj-formc.kpu.go.id\/a12e\/pemilu\/ppwp\/71\/06\/08\/20\/04\/7106082004005-20240216-095055--e3922ed1-3cb0-4994-afa1-59ceba166f9d.jpg"],"administrasi":{"suara_sah":225,"suara_total":226,"pemilih_dpt_j":261,"pemilih_dpt_l":117,"pemilih_dpt_p":144,"pengguna_dpt_j":223,"pengguna_dpt_l":96,"pengguna_dpt_p":127,"pengguna_dptb_j":0,"pengguna_dptb_l":0,"pengguna_dptb_p":0,"suara_tidak_sah":1,"pengguna_total_j":226,"pengguna_total_l":98,"pengguna_total_p":128,"pengguna_non_dpt_j":3,"pengguna_non_dpt_l":2,"pengguna_non_dpt_p":1},"psu":null,"ts":"2024-02-16 12:51:22","status_suara":true,"status_adm":true}},"7106082004006":{"kode_prov":"71","kode_kab":"7106","kode_kec":"710608","kode_kel":"7106082004","kode_tps":"7106082004006","data_tps":{"chart":{"null":null,"100025":4,"100026":158,"100027":69},"images":["https:\/\/sirekap-obj-formc.kpu.go.id\/8d98\/pemilu\/ppwp\/71\/06\/08\/20\/04\/7106082004006-20240215-203758--55d48ae6-2fa5-4d0a-a96d-69b5d06e2c5a.jpg","https:\/\/sirekap-obj-formc.kpu.go.id\/8d98\/pemilu\/ppwp\/71\/06\/08\/20\/04\/7106082004006-20240215-052118--6cc964f2-fd33-45b4-af2e-4d2370205f33.jpg","https:\/\/sirekap-obj-formc.kpu.go.id\/8d98\/pemilu\/ppwp\/71\/06\/08\/20\/04\/7106082004006-20240215-052731--172ca8f2-f9d9-4752-ba20-bb53c842cd59.jpg"],"administrasi":{"suara_sah":235,"suara_total":239,"pemilih_dpt_j":270,"pemilih_dpt_l":132,"pemilih_dpt_p":138,"pengguna_dpt_j":233,"pengguna_dpt_l":120,"pengguna_dpt_p":113,"pengguna_dptb_j":1,"pengguna_dptb_l":1,"pengguna_dptb_p":0,"suara_tidak_sah":4,"pengguna_total_j":235,"pengguna_total_l":121,"pengguna_total_p":113,"pengguna_non_dpt_j":1,"pengguna_non_dpt_l":1,"pengguna_non_dpt_p":0},"psu":null,"ts":"2024-02-15 22:30:27","status_suara":true,"status_adm":true}},"7106082004007":{"kode_prov":"71","kode_kab":"7106","kode_kec":"710608","kode_kel":"7106082004","kode_tps":"7106082004007","data_tps":{"mode":"hhcw","chart":{"null":null,"100025":4,"100026":152,"100027":71},"images":["https:\/\/sirekap-obj-formc.kpu.go.id\/85f0\/pemilu\/ppwp\/71\/06\/08\/20\/04\/7106082004007-20240216-142406--4d2709fc-2394-4a41-b1d8-c10d0286d852.jpg","https:\/\/sirekap-obj-formc.kpu.go.id\/85f0\/pemilu\/ppwp\/71\/06\/08\/20\/04\/7106082004007-20240216-142407--b404aff5-2aa8-4f06-9db5-fd7992f5005b.jpg","https:\/\/sirekap-obj-formc.kpu.go.id\/85f0\/pemilu\/ppwp\/71\/06\/08\/20\/04\/7106082004007-20240216-142406--b7f61888-5e2a-4603-81f2-7dea64e5739c.jpg"],"administrasi":{"suara_sah":227,"suara_total":228,"pemilih_dpt_j":262,"pemilih_dpt_l":128,"pemilih_dpt_p":134,"pengguna_dpt_j":222,"pengguna_dpt_l":104,"pengguna_dpt_p":118,"pengguna_dptb_j":0,"pengguna_dptb_l":0,"pengguna_dptb_p":0,"suara_tidak_sah":1,"pengguna_total_j":228,"pengguna_total_l":107,"pengguna_total_p":121,"pengguna_non_dpt_j":6,"pengguna_non_dpt_l":3,"pengguna_non_dpt_p":3},"psu":null,"ts":"2024-02-16 16:25:10","status_suara":true,"status_adm":true}},"7106082004008":{"kode_prov":"71","kode_kab":"7106","kode_kec":"710608","kode_kel":"7106082004","kode_tps":"7106082004008","data_tps":{"chart":{"null":null,"100025":10,"100026":170,"100027":53},"images":["https:\/\/sirekap-obj-formc.kpu.go.id\/6281\/pemilu\/ppwp\/71\/06\/08\/20\/04\/7106082004008-20240215-032729--3a9a111d-97b2-4964-8cfa-59dec512388c.jpg","https:\/\/sirekap-obj-formc.kpu.go.id\/6281\/pemilu\/ppwp\/71\/06\/08\/20\/04\/7106082004008-20240215-034911--33e5c0b8-a0e3-4cd1-8e08-66742a5c7f4e.jpg","https:\/\/sirekap-obj-formc.kpu.go.id\/6281\/pemilu\/ppwp\/71\/06\/08\/20\/04\/7106082004008-20240215-035020--93f4ed33-21fc-45b3-a1d8-7c6cee9e2fd2.jpg"],"administrasi":{"suara_sah":233,"suara_total":236,"pemilih_dpt_j":254,"pemilih_dpt_l":120,"pemilih_dpt_p":134,"pengguna_dpt_j":210,"pengguna_dpt_l":101,"pengguna_dpt_p":109,"pengguna_dptb_j":0,"pengguna_dptb_l":0,"pengguna_dptb_p":0,"suara_tidak_sah":3,"pengguna_total_j":236,"pengguna_total_l":114,"pengguna_total_p":122,"pengguna_non_dpt_j":26,"pengguna_non_dpt_l":13,"pengguna_non_dpt_p":13},"psu":null,"ts":"2024-02-15 23:29:50","status_suara":true,"status_adm":true}},"7106082008001":{"kode_prov":"71","kode_kab":"7106","kode_kec":"710608","kode_kel":"7106082008","kode_tps":"7106082008001","data_tps":{"mode":"hhcw","chart":{"null":null,"100025":4,"100026":188,"100027":32},"images":["https:\/\/sirekap-obj-formc.kpu.go.id\/e8ed\/pemilu\/ppwp\/71\/06\/08\/20\/08\/7106082008001-20240218-203920--fbc640ad-3a17-4111-b566-a3794b4f377c.jpg","https:\/\/sirekap-obj-formc.kpu.go.id\/e8ed\/pemilu\/ppwp\/71\/06\/08\/20\/08\/7106082008001-20240218-204045--5eef452e-8454-46fe-80cd-36d5c3d2aa64.jpg","https:\/\/sirekap-obj-formc.kpu.go.id\/e8ed\/pemilu\/ppwp\/71\/06\/08\/20\/08\/7106082008001-20240218-204209--c4ee028a-8dbe-4338-9fc3-4435843f58d8.jpg"],"administrasi":{"suara_sah":224,"suara_total":228,"pemilih_dpt_j":288,"pemilih_dpt_l":135,"pemilih_dpt_p":153,"pengguna_dpt_j":221,"pengguna_dpt_l":98,"pengguna_dpt_p":123,"pengguna_dptb_j":3,"pengguna_dptb_l":2,"pengguna_dptb_p":1,"suara_tidak_sah":4,"pengguna_total_j":228,"pengguna_total_l":102,"pengguna_total_p":126,"pengguna_non_dpt_j":4,"pengguna_non_dpt_l":2,"pengguna_non_dpt_p":2},"psu":null,"ts":"2024-02-19 06:16:00","status_suara":true,"status_adm":true}},"7106082008002":{"kode_prov":"71","kode_kab":"7106","kode_kec":"710608","kode_kel":"7106082008","kode_tps":"7106082008002","data_tps":{"chart":{"null":null,"100025":9,"100026":164,"100027":41},"images":["https:\/\/sirekap-obj-formc.kpu.go.id\/ceb4\/pemilu\/ppwp\/71\/06\/08\/20\/08\/7106082008002-20240215-065941--8f90c533-0ed7-4ae7-a648-e846f75389ab.jpg","https:\/\/sirekap-obj-formc.kpu.go.id\/ceb4\/pemilu\/ppwp\/71\/06\/08\/20\/08\/7106082008002-20240215-082724--53b84113-25ac-49e1-b1cc-f9617255a385.jpg","https:\/\/sirekap-obj-formc.kpu.go.id\/ceb4\/pemilu\/ppwp\/71\/06\/08\/20\/08\/7106082008002-20240215-082122--854db634-138a-44d9-bea6-18c2ec77b9ef.jpg"],"administrasi":{"suara_sah":214,"suara_total":215,"pemilih_dpt_j":272,"pemilih_dpt_l":122,"pemilih_dpt_p":150,"pengguna_dpt_j":210,"pengguna_dpt_l":84,"pengguna_dpt_p":126,"pengguna_dptb_j":0,"pengguna_dptb_l":0,"pengguna_dptb_p":0,"suara_tidak_sah":1,"pengguna_total_j":215,"pengguna_total_l":87,"pengguna_total_p":128,"pengguna_non_dpt_j":5,"pengguna_non_dpt_l":3,"pengguna_non_dpt_p":2},"psu":null,"ts":"2024-02-15 20:30:46","status_suara":true,"status_adm":true}},"7106082008003":{"kode_prov":"71","kode_kab":"7106","kode_kec":"710608","kode_kel":"7106082008","kode_tps":"7106082008003","data_tps":{"chart":{"null":null,"100025":5,"100026":173,"100027":30},"images":["https:\/\/sirekap-obj-formc.kpu.go.id\/c39b\/pemilu\/ppwp\/71\/06\/08\/20\/08\/7106082008003-20240215-062125--167ab1dc-0739-41bf-95d5-5b76c3d0d0f8.jpg","https:\/\/sirekap-obj-formc.kpu.go.id\/c39b\/pemilu\/ppwp\/71\/06\/08\/20\/08\/7106082008003-20240215-002217--580d5224-01e7-4f51-be88-bfde6caab222.jpg","https:\/\/sirekap-obj-formc.kpu.go.id\/c39b\/pemilu\/ppwp\/71\/06\/08\/20\/08\/7106082008003-20240215-062846--41738b16-2f36-4d82-9c32-45e3d3e36f10.jpg"],"administrasi":{"suara_sah":208,"suara_total":209,"pemilih_dpt_j":265,"pemilih_dpt_l":128,"pemilih_dpt_p":137,"pengguna_dpt_j":209,"pengguna_dpt_l":97,"pengguna_dpt_p":112,"pengguna_dptb_j":0,"pengguna_dptb_l":0,"pengguna_dptb_p":0,"suara_tidak_sah":1,"pengguna_total_j":209,"pengguna_total_l":97,"pengguna_total_p":112,"pengguna_non_dpt_j":0,"pengguna_non_dpt_l":0,"pengguna_non_dpt_p":0},"psu":null,"ts":"2024-02-15 20:30:46","status_suara":true,"status_adm":true}},"7106082008004":{"kode_prov":"71","kode_kab":"7106","kode_kec":"710608","kode_kel":"7106082008","kode_tps":"7106082008004","data_tps":{"mode":"hhcw","chart":{"null":null,"100025":18,"100026":162,"100027":28},"images":["https:\/\/sirekap-obj-formc.kpu.go.id\/b769\/pemilu\/ppwp\/71\/06\/08\/20\/08\/7106082008004-20240218-161247--3f228fc9-269a-47c3-9ee5-c0ef8015b78e.jpg","https:\/\/sirekap-obj-formc.kpu.go.id\/b769\/pemilu\/ppwp\/71\/06\/08\/20\/08\/7106082008004-20240218-161331--6bfe8287-96ed-4a85-af58-82a3a430ccb4.jpg","https:\/\/sirekap-obj-formc.kpu.go.id\/b769\/pemilu\/ppwp\/71\/06\/08\/20\/08\/7106082008004-20240218-161418--7d04dd63-56b8-4aa5-a4dd-7876df7e1cb8.jpg"],"administrasi":{"suara_sah":208,"suara_total":212,"pemilih_dpt_j":265,"pemilih_dpt_l":126,"pemilih_dpt_p":139,"pengguna_dpt_j":210,"pengguna_dpt_l":100,"pengguna_dpt_p":110,"pengguna_dptb_j":2,"pengguna_dptb_l":1,"pengguna_dptb_p":1,"suara_tidak_sah":4,"pengguna_total_j":212,"pengguna_total_l":101,"pengguna_total_p":111,"pengguna_non_dpt_j":0,"pengguna_non_dpt_l":0,"pengguna_non_dpt_p":0},"psu":null,"ts":"2024-02-19 06:16:00","status_suara":true,"status_adm":true}},"7106082008005":{"kode_prov":"71","kode_kab":"7106","kode_kec":"710608","kode_kel":"7106082008","kode_tps":"7106082008005","data_tps":{"chart":{"null":null,"100025":10,"100026":172,"100027":41},"images":["https:\/\/sirekap-obj-formc.kpu.go.id\/ed7c\/pemilu\/ppwp\/71\/06\/08\/20\/08\/7106082008005-20240215-040039--f265b0bb-3a99-42a5-ac1d-f82abca70a86.jpg","https:\/\/sirekap-obj-formc.kpu.go.id\/ed7c\/pemilu\/ppwp\/71\/06\/08\/20\/08\/7106082008005-20240215-040143--ce3c2419-2684-46b6-8c3e-ec32ff008c55.jpg","https:\/\/sirekap-obj-formc.kpu.go.id\/ed7c\/pemilu\/ppwp\/71\/06\/08\/20\/08\/7106082008005-20240215-040251--0345f86a-6eb4-43cd-99e2-a1fdce4c2185.jpg"],"administrasi":{"suara_sah":223,"suara_total":224,"pemilih_dpt_j":272,"pemilih_dpt_l":131,"pemilih_dpt_p":141,"pengguna_dpt_j":224,"pengguna_dpt_l":103,"pengguna_dpt_p":121,"pengguna_dptb_j":0,"pengguna_dptb_l":0,"pengguna_dptb_p":0,"suara_tidak_sah":1,"pengguna_total_j":224,"pengguna_total_l":103,"pengguna_total_p":121,"pengguna_non_dpt_j":0,"pengguna_non_dpt_l":0,"pengguna_non_dpt_p":0},"psu":null,"ts":"2024-02-15 15:00:29","status_suara":true,"status_adm":true}},"7106082008006":{"kode_prov":"71","kode_kab":"7106","kode_kec":"710608","kode_kel":"7106082008","kode_tps":"7106082008006","data_tps":{"chart":{"null":null,"100025":10,"100026":168,"100027":44},"images":["https:\/\/sirekap-obj-formc.kpu.go.id\/63f4\/pemilu\/ppwp\/71\/06\/08\/20\/08\/7106082008006-20240215-023135--4f117af0-2aec-4e03-8682-55bfdbc4f5ee.jpg","https:\/\/sirekap-obj-formc.kpu.go.id\/63f4\/pemilu\/ppwp\/71\/06\/08\/20\/08\/7106082008006-20240215-023142--aa9a30c1-3e59-4dff-8ca2-54591fd0fc9b.jpg","https:\/\/sirekap-obj-formc.kpu.go.id\/63f4\/pemilu\/ppwp\/71\/06\/08\/20\/08\/7106082008006-20240215-023147--e24bcc4e-be7e-4b09-a2b2-59e82e2b7e2f.jpg"],"administrasi":{"suara_sah":222,"suara_total":222,"pemilih_dpt_j":273,"pemilih_dpt_l":128,"pemilih_dpt_p":145,"pengguna_dpt_j":217,"pengguna_dpt_l":100,"pengguna_dpt_p":117,"pengguna_dptb_j":0,"pengguna_dptb_l":0,"pengguna_dptb_p":0,"suara_tidak_sah":0,"pengguna_total_j":222,"pengguna_total_l":102,"pengguna_total_p":120,"pengguna_non_dpt_j":5,"pengguna_non_dpt_l":2,"pengguna_non_dpt_p":3},"psu":null,"ts":"2024-02-15 21:30:27","status_suara":true,"status_adm":true}},"7106082008007":{"kode_prov":"71","kode_kab":"7106","kode_kec":"710608","kode_kel":"7106082008","kode_tps":"7106082008007","data_tps":{"mode":"hhcw","chart":{"null":null,"100025":6,"100026":182,"100027":47},"images":["https:\/\/sirekap-obj-formc.kpu.go.id\/992d\/pemilu\/ppwp\/71\/06\/08\/20\/08\/7106082008007-20240217-145927--de049bba-04bd-4531-a80c-42f87416fb21.jpg","https:\/\/sirekap-obj-formc.kpu.go.id\/992d\/pemilu\/ppwp\/71\/06\/08\/20\/08\/7106082008007-20240217-151833--7865cfb7-a8e6-43db-b684-a6e5df4a99f0.jpg","https:\/\/sirekap-obj-formc.kpu.go.id\/992d\/pemilu\/ppwp\/71\/06\/08\/20\/08\/7106082008007-20240217-152001--c432c364-5efc-4bb9-9498-336778d08fc3.jpg"],"administrasi":{"suara_sah":235,"suara_total":237,"pemilih_dpt_j":279,"pemilih_dpt_l":133,"pemilih_dpt_p":146,"pengguna_dpt_j":234,"pengguna_dpt_l":109,"pengguna_dpt_p":126,"pengguna_dptb_j":0,"pengguna_dptb_l":0,"pengguna_dptb_p":0,"suara_tidak_sah":2,"pengguna_total_j":237,"pengguna_total_l":108,"pengguna_total_p":129,"pengguna_non_dpt_j":3,"pengguna_non_dpt_l":0,"pengguna_non_dpt_p":3},"psu":null,"ts":"2024-02-19 06:16:00","status_suara":true,"status_adm":true}},"7106082008008":{"kode_prov":"71","kode_kab":"7106","kode_kec":"710608","kode_kel":"7106082008","kode_tps":"7106082008008","data_tps":{"chart":{"null":null,"100025":9,"100026":170,"100027":41},"images":["https:\/\/sirekap-obj-formc.kpu.go.id\/6d39\/pemilu\/ppwp\/71\/06\/08\/20\/08\/7106082008008-20240215-081647--b50bf696-65bb-4c16-918d-34a0ab9c7456.jpg","https:\/\/sirekap-obj-formc.kpu.go.id\/6d39\/pemilu\/ppwp\/71\/06\/08\/20\/08\/7106082008008-20240214-231853--2212b023-e606-4b08-9230-a2762c3608d2.jpg","https:\/\/sirekap-obj-formc.kpu.go.id\/6d39\/pemilu\/ppwp\/71\/06\/08\/20\/08\/7106082008008-20240214-231946--997e5d2d-2f3c-4bd9-8e66-4c4e9853f8c1.jpg"],"administrasi":null,"psu":null,"ts":"2024-02-15 22:30:27","status_suara":true,"status_adm":false}},"7106082008009":{"kode_prov":"71","kode_kab":"7106","kode_kec":"710608","kode_kel":"7106082008","kode_tps":"7106082008009","data_tps":{"mode":"hhcw","chart":{"null":null,"100025":7,"100026":193,"100027":32},"images":["https:\/\/sirekap-obj-formc.kpu.go.id\/a51a\/pemilu\/ppwp\/71\/06\/08\/20\/08\/7106082008009-20240217-144613--76e11dc4-5086-4a6b-baa0-ea22f0a86773.jpg","https:\/\/sirekap-obj-formc.kpu.go.id\/a51a\/pemilu\/ppwp\/71\/06\/08\/20\/08\/7106082008009-20240217-144737--e8c2b8ce-5de3-4bfa-8221-19e7a0705907.jpg","https:\/\/sirekap-obj-formc.kpu.go.id\/a51a\/pemilu\/ppwp\/71\/06\/08\/20\/08\/7106082008009-20240217-145000--daed1ef4-6ecf-48d7-892d-7c3114392c34.jpg"],"administrasi":{"suara_sah":232,"suara_total":232,"pemilih_dpt_j":275,"pemilih_dpt_l":131,"pemilih_dpt_p":144,"pengguna_dpt_j":227,"pengguna_dpt_l":111,"pengguna_dpt_p":116,"pengguna_dptb_j":0,"pengguna_dptb_l":0,"pengguna_dptb_p":0,"suara_tidak_sah":0,"pengguna_total_j":232,"pengguna_total_l":114,"pengguna_total_p":118,"pengguna_non_dpt_j":5,"pengguna_non_dpt_l":3,"pengguna_non_dpt_p":2},"psu":null,"ts":"2024-02-17 16:00:02","status_suara":true,"status_adm":true}},"7106082008010":{"kode_prov":"71","kode_kab":"7106","kode_kec":"710608","kode_kel":"7106082008","kode_tps":"7106082008010","data_tps":{"chart":{"null":null,"100025":12,"100026":179,"100027":41},"images":["https:\/\/sirekap-obj-formc.kpu.go.id\/8ab7\/pemilu\/ppwp\/71\/06\/08\/20\/08\/7106082008010-20240214-202613--12955260-2aa3-48d9-97d6-0a61d553d23c.jpg","https:\/\/sirekap-obj-formc.kpu.go.id\/8ab7\/pemilu\/ppwp\/71\/06\/08\/20\/08\/7106082008010-20240214-202903--5e251289-c88e-451c-93a9-99d64261f130.jpg","https:\/\/sirekap-obj-formc.kpu.go.id\/8ab7\/pemilu\/ppwp\/71\/06\/08\/20\/08\/7106082008010-20240214-203028--5d323cc4-ae3c-4476-a529-8e51b9d7b5e3.jpg"],"administrasi":null,"psu":null,"ts":"2024-02-14 21:46:01","status_suara":true,"status_adm":false}},"7106082008011":{"kode_prov":"71","kode_kab":"7106","kode_kec":"710608","kode_kel":"7106082008","kode_tps":"7106082008011","data_tps":{"chart":{"null":null,"100025":5,"100026":182,"100027":34},"images":["https:\/\/sirekap-obj-formc.kpu.go.id\/4c76\/pemilu\/ppwp\/71\/06\/08\/20\/08\/7106082008011-20240215-012219--63da5de0-3e94-4e65-936c-143deb66df5f.jpg","https:\/\/sirekap-obj-formc.kpu.go.id\/4c76\/pemilu\/ppwp\/71\/06\/08\/20\/08\/7106082008011-20240215-012742--7802591a-bbd5-492f-93bc-89bde3ac2124.jpg","https:\/\/sirekap-obj-formc.kpu.go.id\/4c76\/pemilu\/ppwp\/71\/06\/08\/20\/08\/7106082008011-20240215-013003--6c83dd64-2d87-4c39-add0-348456086f5f.jpg"],"administrasi":{"suara_sah":221,"suara_total":222,"pemilih_dpt_j":257,"pemilih_dpt_l":130,"pemilih_dpt_p":127,"pengguna_dpt_j":217,"pengguna_dpt_l":107,"pengguna_dpt_p":110,"pengguna_dptb_j":0,"pengguna_dptb_l":0,"pengguna_dptb_p":0,"suara_tidak_sah":1,"pengguna_total_j":222,"pengguna_total_l":108,"pengguna_total_p":114,"pengguna_non_dpt_j":5,"pengguna_non_dpt_l":1,"pengguna_non_dpt_p":4},"psu":null,"ts":"2024-02-15 21:01:18","status_suara":true,"status_adm":true}},"7106082008012":{"kode_prov":"71","kode_kab":"7106","kode_kec":"710608","kode_kel":"7106082008","kode_tps":"7106082008012","data_tps":{"chart":{"null":null,"100025":8,"100026":122,"100027":26},"images":["https:\/\/sirekap-obj-formc.kpu.go.id\/8332\/pemilu\/ppwp\/71\/06\/08\/20\/08\/7106082008012-20240214-212012--eab4bd0c-2d3d-47a5-ab22-1d4cfb63ceac.jpg","https:\/\/sirekap-obj-formc.kpu.go.id\/8332\/pemilu\/ppwp\/71\/06\/08\/20\/08\/7106082008012-20240214-232338--1b25c44a-a5b7-4cef-a0a9-4c6f4e3137c0.jpg","https:\/\/sirekap-obj-formc.kpu.go.id\/8332\/pemilu\/ppwp\/71\/06\/08\/20\/08\/7106082008012-20240214-212314--5d942c90-7eb2-436f-8c39-e7f673e6cb59.jpg"],"administrasi":null,"psu":null,"ts":"2024-02-15 19:00:26","status_suara":true,"status_adm":false}},"7106082002001":{"kode_prov":"71","kode_kab":"7106","kode_kec":"710608","kode_kel":"7106082002","kode_tps":"7106082002001","data_tps":{"mode":"hhcw","chart":{"null":null,"100025":0,"100026":140,"100027":74},"images":["https:\/\/sirekap-obj-formc.kpu.go.id\/a573\/pemilu\/ppwp\/71\/06\/08\/20\/02\/7106082002001-20240217-142621--18ccc016-ad4c-4855-bfeb-03b6ba80936e.jpg","https:\/\/sirekap-obj-formc.kpu.go.id\/a573\/pemilu\/ppwp\/71\/06\/08\/20\/02\/7106082002001-20240217-142642--1849e4bf-a4dd-40e7-a754-4b1b8ecf3e4e.jpg","https:\/\/sirekap-obj-formc.kpu.go.id\/a573\/pemilu\/ppwp\/71\/06\/08\/20\/02\/7106082002001-20240217-142657--22afdaad-1277-488e-a7d8-c92e2b1ab277.jpg"],"administrasi":{"suara_sah":214,"suara_total":215,"pemilih_dpt_j":250,"pemilih_dpt_l":119,"pemilih_dpt_p":131,"pengguna_dpt_j":214,"pengguna_dpt_l":103,"pengguna_dpt_p":111,"pengguna_dptb_j":0,"pengguna_dptb_l":0,"pengguna_dptb_p":0,"suara_tidak_sah":1,"pengguna_total_j":215,"pengguna_total_l":104,"pengguna_total_p":111,"pengguna_non_dpt_j":1,"pengguna_non_dpt_l":1,"pengguna_non_dpt_p":0},"psu":null,"ts":"2024-02-17 14:45:18","status_suara":true,"status_adm":true}},"7106082002002":{"kode_prov":"71","kode_kab":"7106","kode_kec":"710608","kode_kel":"7106082002","kode_tps":"7106082002002","data_tps":{"mode":"hhcw","chart":{"null":null,"100025":1,"100026":149,"100027":79},"images":["https:\/\/sirekap-obj-formc.kpu.go.id\/6f82\/pemilu\/ppwp\/71\/06\/08\/20\/02\/7106082002002-20240217-170229--8c8fc114-9c75-415b-bba6-35bfb3896bc7.jpg","https:\/\/sirekap-obj-formc.kpu.go.id\/6f82\/pemilu\/ppwp\/71\/06\/08\/20\/02\/7106082002002-20240217-170211--3a9d793a-f667-4e59-8b57-66a134fa11ff.jpg","https:\/\/sirekap-obj-formc.kpu.go.id\/6f82\/pemilu\/ppwp\/71\/06\/08\/20\/02\/7106082002002-20240217-170154--4adcc1db-80da-4d08-8bbf-a03fdd00eabe.jpg"],"administrasi":{"suara_sah":229,"suara_total":230,"pemilih_dpt_j":253,"pemilih_dpt_l":121,"pemilih_dpt_p":132,"pengguna_dpt_j":228,"pengguna_dpt_l":108,"pengguna_dpt_p":120,"pengguna_dptb_j":0,"pengguna_dptb_l":0,"pengguna_dptb_p":0,"suara_tidak_sah":1,"pengguna_total_j":230,"pengguna_total_l":109,"pengguna_total_p":121,"pengguna_non_dpt_j":2,"pengguna_non_dpt_l":1,"pengguna_non_dpt_p":1},"psu":null,"ts":"2024-02-17 17:30:00","status_suara":true,"status_adm":true}},"7106082002003":{"kode_prov":"71","kode_kab":"7106","kode_kec":"710608","kode_kel":"7106082002","kode_tps":"7106082002003","data_tps":{"mode":"hhcw","chart":{"null":null,"100025":3,"100026":144,"100027":72},"images":["https:\/\/sirekap-obj-formc.kpu.go.id\/ed64\/pemilu\/ppwp\/71\/06\/08\/20\/02\/7106082002003-20240217-183546--c2178c11-362f-4f9c-9c87-8fb8ede55159.jpg","https:\/\/sirekap-obj-formc.kpu.go.id\/ed64\/pemilu\/ppwp\/71\/06\/08\/20\/02\/7106082002003-20240217-183623--7c59f238-459a-426b-a173-f212c41f0383.jpg","https:\/\/sirekap-obj-formc.kpu.go.id\/ed64\/pemilu\/ppwp\/71\/06\/08\/20\/02\/7106082002003-20240217-183735--6dfb98ff-2f92-4056-9318-f9443858139c.jpg"],"administrasi":{"suara_sah":219,"suara_total":223,"pemilih_dpt_j":251,"pemilih_dpt_l":125,"pemilih_dpt_p":126,"pengguna_dpt_j":222,"pengguna_dpt_l":109,"pengguna_dpt_p":113,"pengguna_dptb_j":1,"pengguna_dptb_l":1,"pengguna_dptb_p":0,"suara_tidak_sah":4,"pengguna_total_j":223,"pengguna_total_l":110,"pengguna_total_p":113,"pengguna_non_dpt_j":0,"pengguna_non_dpt_l":0,"pengguna_non_dpt_p":0},"psu":null,"ts":"2024-02-17 19:00:04","status_suara":true,"status_adm":true}},"7106082005001":{"kode_prov":"71","kode_kab":"7106","kode_kec":"710608","kode_kel":"7106082005","kode_tps":"7106082005001","data_tps":{"mode":"hhcw","chart":{"null":null,"100025":2,"100026":171,"100027":81},"images":["https:\/\/sirekap-obj-formc.kpu.go.id\/cd6a\/pemilu\/ppwp\/71\/06\/08\/20\/05\/7106082005001-20240218-120636--a04272d4-27cc-423d-b1f8-0a41e96e8073.jpg","https:\/\/sirekap-obj-formc.kpu.go.id\/cd6a\/pemilu\/ppwp\/71\/06\/08\/20\/05\/7106082005001-20240218-120805--bf10c319-3196-4ee2-bb7b-3040a6bc7932.jpg","https:\/\/sirekap-obj-formc.kpu.go.id\/cd6a\/pemilu\/ppwp\/71\/06\/08\/20\/05\/7106082005001-20240218-120928--418904c4-9c7a-487b-9bba-32b34b3c068d.jpg"],"administrasi":{"suara_sah":254,"suara_total":254,"pemilih_dpt_j":287,"pemilih_dpt_l":135,"pemilih_dpt_p":152,"pengguna_dpt_j":253,"pengguna_dpt_l":115,"pengguna_dpt_p":138,"pengguna_dptb_j":0,"pengguna_dptb_l":0,"pengguna_dptb_p":0,"suara_tidak_sah":0,"pengguna_total_j":254,"pengguna_total_l":115,"pengguna_total_p":139,"pengguna_non_dpt_j":1,"pengguna_non_dpt_l":0,"pengguna_non_dpt_p":1},"psu":null,"ts":"2024-02-19 06:16:00","status_suara":true,"status_adm":true}},"7106082005002":{"kode_prov":"71","kode_kab":"7106","kode_kec":"710608","kode_kel":"7106082005","kode_tps":"7106082005002","data_tps":{"mode":"hhcw","chart":{"null":null,"100025":1,"100026":193,"100027":53},"images":["https:\/\/sirekap-obj-formc.kpu.go.id\/44b6\/pemilu\/ppwp\/71\/06\/08\/20\/05\/7106082005002-20240218-123352--b69ace19-ba2c-4b29-8127-a8bda88faea2.jpg","https:\/\/sirekap-obj-formc.kpu.go.id\/44b6\/pemilu\/ppwp\/71\/06\/08\/20\/05\/7106082005002-20240218-123214--3623eba4-6fb3-46af-9fe9-82d382eb3e50.jpg","https:\/\/sirekap-obj-formc.kpu.go.id\/44b6\/pemilu\/ppwp\/71\/06\/08\/20\/05\/7106082005002-20240218-123525--4f0af551-65ba-431d-ab18-2a463e0cae1b.jpg"],"administrasi":{"suara_sah":247,"suara_total":248,"pemilih_dpt_j":286,"pemilih_dpt_l":142,"pemilih_dpt_p":144,"pengguna_dpt_j":238,"pengguna_dpt_l":112,"pengguna_dpt_p":126,"pengguna_dptb_j":5,"pengguna_dptb_l":2,"pengguna_dptb_p":3,"suara_tidak_sah":1,"pengguna_total_j":248,"pengguna_total_l":116,"pengguna_total_p":132,"pengguna_non_dpt_j":5,"pengguna_non_dpt_l":2,"pengguna_non_dpt_p":3},"psu":null,"ts":"2024-02-19 06:16:00","status_suara":true,"status_adm":true}},"7106082005003":{"kode_prov":"71","kode_kab":"7106","kode_kec":"710608","kode_kel":"7106082005","kode_tps":"7106082005003","data_tps":{"chart":{"null":null,"100025":2,"100026":187,"100027":45},"images":["https:\/\/sirekap-obj-formc.kpu.go.id\/2f80\/pemilu\/ppwp\/71\/06\/08\/20\/05\/7106082005003-20240215-080414--1b83cfbc-4a27-46d6-b4ad-d612146f710e.jpg","https:\/\/sirekap-obj-formc.kpu.go.id\/2f80\/pemilu\/ppwp\/71\/06\/08\/20\/05\/7106082005003-20240215-080440--734d0aae-76e4-45cd-84e9-8db44ed7fa4d.jpg","https:\/\/sirekap-obj-formc.kpu.go.id\/2f80\/pemilu\/ppwp\/71\/06\/08\/20\/05\/7106082005003-20240215-080503--da85b83f-1784-4ba5-9310-0c4dfe009986.jpg"],"administrasi":{"suara_sah":234,"suara_total":235,"pemilih_dpt_j":273,"pemilih_dpt_l":140,"pemilih_dpt_p":133,"pengguna_dpt_j":233,"pengguna_dpt_l":111,"pengguna_dpt_p":122,"pengguna_dptb_j":1,"pengguna_dptb_l":0,"pengguna_dptb_p":1,"suara_tidak_sah":1,"pengguna_total_j":235,"pengguna_total_l":111,"pengguna_total_p":124,"pengguna_non_dpt_j":1,"pengguna_non_dpt_l":0,"pengguna_non_dpt_p":1},"psu":null,"ts":"2024-02-15 23:29:50","status_suara":true,"status_adm":true}},"7106082005004":{"kode_prov":"71","kode_kab":"7106","kode_kec":"710608","kode_kel":"7106082005","kode_tps":"7106082005004","data_tps":{"chart":{"null":null,"100025":1,"100026":206,"100027":28},"images":["https:\/\/sirekap-obj-formc.kpu.go.id\/28d4\/pemilu\/ppwp\/71\/06\/08\/20\/05\/7106082005004-20240215-015227--a3e399a5-ebf9-4211-9e5e-e874e33675c1.jpg","https:\/\/sirekap-obj-formc.kpu.go.id\/28d4\/pemilu\/ppwp\/71\/06\/08\/20\/05\/7106082005004-20240215-020716--9926ff52-2d78-47db-84e7-5f4f18684f4f.jpg","https:\/\/sirekap-obj-formc.kpu.go.id\/28d4\/pemilu\/ppwp\/71\/06\/08\/20\/05\/7106082005004-20240215-020740--6d434859-762c-40e2-91a5-27a34d081bca.jpg"],"administrasi":{"suara_sah":235,"suara_total":281,"pemilih_dpt_j":275,"pemilih_dpt_l":144,"pemilih_dpt_p":131,"pengguna_dpt_j":230,"pengguna_dpt_l":114,"pengguna_dpt_p":116,"pengguna_dptb_j":5,"pengguna_dptb_l":3,"pengguna_dptb_p":2,"suara_tidak_sah":46,"pengguna_total_j":235,"pengguna_total_l":117,"pengguna_total_p":118,"pengguna_non_dpt_j":0,"pengguna_non_dpt_l":0,"pengguna_non_dpt_p":0},"psu":null,"ts":"2024-02-15 20:30:46","status_suara":true,"status_adm":true}},"7106082005005":{"kode_prov":"71","kode_kab":"7106","kode_kec":"710608","kode_kel":"7106082005","kode_tps":"7106082005005","data_tps":{"mode":"hhcw","chart":{"null":null,"100025":3,"100026":171,"100027":35},"images":["https:\/\/sirekap-obj-formc.kpu.go.id\/ccb4\/pemilu\/ppwp\/71\/06\/08\/20\/05\/7106082005005-20240218-124926--a2a111d0-bd51-454b-9b0f-f6a887188d99.jpg","https:\/\/sirekap-obj-formc.kpu.go.id\/ccb4\/pemilu\/ppwp\/71\/06\/08\/20\/05\/7106082005005-20240218-125706--50f40e37-5160-402d-b69b-e366860ff7d4.jpg","https:\/\/sirekap-obj-formc.kpu.go.id\/ccb4\/pemilu\/ppwp\/71\/06\/08\/20\/05\/7106082005005-20240218-130004--b03585b9-e58d-4bfb-99e1-da4dcafbd6ed.jpg"],"administrasi":{"suara_sah":209,"suara_total":211,"pemilih_dpt_j":263,"pemilih_dpt_l":124,"pemilih_dpt_p":139,"pengguna_dpt_j":263,"pengguna_dpt_l":124,"pengguna_dpt_p":139,"pengguna_dptb_j":0,"pengguna_dptb_l":0,"pengguna_dptb_p":0,"suara_tidak_sah":2,"pengguna_total_j":263,"pengguna_total_l":124,"pengguna_total_p":139,"pengguna_non_dpt_j":0,"pengguna_non_dpt_l":0,"pengguna_non_dpt_p":0},"psu":null,"ts":"2024-02-19 06:16:00","status_suara":true,"status_adm":true}},"7106082005006":{"kode_prov":"71","kode_kab":"7106","kode_kec":"710608","kode_kel":"7106082005","kode_tps":"7106082005006","data_tps":{"chart":{"null":null,"100025":4,"100026":179,"100027":34},"images":["https:\/\/sirekap-obj-formc.kpu.go.id\/66c7\/pemilu\/ppwp\/71\/06\/08\/20\/05\/7106082005006-20240215-090048--9932bca6-8b24-440f-bd49-eb0e0f67caa0.jpg","https:\/\/sirekap-obj-formc.kpu.go.id\/66c7\/pemilu\/ppwp\/71\/06\/08\/20\/05\/7106082005006-20240215-090248--5243999b-7547-4437-bee2-007e71bfb8ff.jpg","https:\/\/sirekap-obj-formc.kpu.go.id\/66c7\/pemilu\/ppwp\/71\/06\/08\/20\/05\/7106082005006-20240215-104225--f798de7d-2ea1-4a6a-aa14-2ef42da0f32b.jpg"],"administrasi":{"suara_sah":217,"suara_total":0,"pemilih_dpt_j":268,"pemilih_dpt_l":135,"pemilih_dpt_p":133,"pengguna_dpt_j":212,"pengguna_dpt_l":102,"pengguna_dpt_p":110,"pengguna_dptb_j":1,"pengguna_dptb_l":0,"pengguna_dptb_p":1,"suara_tidak_sah":0,"pengguna_total_j":217,"pengguna_total_l":104,"pengguna_total_p":113,"pengguna_non_dpt_j":4,"pengguna_non_dpt_l":2,"pengguna_non_dpt_p":2},"psu":null,"ts":"2024-02-15 20:30:46","status_suara":true,"status_adm":true}},"7106082005007":{"kode_prov":"71","kode_kab":"7106","kode_kec":"710608","kode_kel":"7106082005","kode_tps":"7106082005007","data_tps":{"chart":{"null":null,"100025":1,"100026":169,"100027":50},"images":["https:\/\/sirekap-obj-formc.kpu.go.id\/1692\/pemilu\/ppwp\/71\/06\/08\/20\/05\/7106082005007-20240215-084313--6df99797-cf5d-48d8-880d-6ca18e4fe26d.jpg","https:\/\/sirekap-obj-formc.kpu.go.id\/1692\/pemilu\/ppwp\/71\/06\/08\/20\/05\/7106082005007-20240216-103915--dc005733-6137-48f3-82ce-5665fdc9a7ae.jpg","https:\/\/sirekap-obj-formc.kpu.go.id\/1692\/pemilu\/ppwp\/71\/06\/08\/20\/05\/7106082005007-20240215-184920--92202ddf-1da8-42b0-ad82-bb7d92239d52.jpg"],"administrasi":{"suara_sah":220,"suara_total":221,"pemilih_dpt_j":275,"pemilih_dpt_l":136,"pemilih_dpt_p":139,"pengguna_dpt_j":220,"pengguna_dpt_l":103,"pengguna_dpt_p":117,"pengguna_dptb_j":0,"pengguna_dptb_l":0,"pengguna_dptb_p":0,"suara_tidak_sah":1,"pengguna_total_j":221,"pengguna_total_l":103,"pengguna_total_p":118,"pengguna_non_dpt_j":1,"pengguna_non_dpt_l":0,"pengguna_non_dpt_p":1},"psu":null,"ts":"2024-02-16 12:51:22","status_suara":true,"status_adm":true}},"7106082005008":{"kode_prov":"71","kode_kab":"7106","kode_kec":"710608","kode_kel":"7106082005","kode_tps":"7106082005008","data_tps":{"chart":{"null":null,"100025":1,"100026":171,"100027":50},"images":["https:\/\/sirekap-obj-formc.kpu.go.id\/9a18\/pemilu\/ppwp\/71\/06\/08\/20\/05\/7106082005008-20240215-073521--6a09c11b-664c-443f-a279-0fba38023a2e.jpg","https:\/\/sirekap-obj-formc.kpu.go.id\/9a18\/pemilu\/ppwp\/71\/06\/08\/20\/05\/7106082005008-20240215-073644--3aa194a3-b1e1-48fc-ad78-61b6f0cfc143.jpg","https:\/\/sirekap-obj-formc.kpu.go.id\/9a18\/pemilu\/ppwp\/71\/06\/08\/20\/05\/7106082005008-20240215-073811--32433429-129c-4d3a-8c4b-f1aa069dd512.jpg"],"administrasi":{"suara_sah":222,"suara_total":225,"pemilih_dpt_j":261,"pemilih_dpt_l":124,"pemilih_dpt_p":137,"pengguna_dpt_j":224,"pengguna_dpt_l":117,"pengguna_dpt_p":107,"pengguna_dptb_j":0,"pengguna_dptb_l":0,"pengguna_dptb_p":0,"suara_tidak_sah":3,"pengguna_total_j":225,"pengguna_total_l":117,"pengguna_total_p":108,"pengguna_non_dpt_j":1,"pengguna_non_dpt_l":0,"pengguna_non_dpt_p":1},"psu":null,"ts":"2024-02-15 22:30:27","status_suara":true,"status_adm":true}},"7106082005009":{"kode_prov":"71","kode_kab":"7106","kode_kec":"710608","kode_kel":"7106082005","kode_tps":"7106082005009","data_tps":{"chart":{"null":null,"100025":3,"100026":155,"100027":51},"images":["https:\/\/sirekap-obj-formc.kpu.go.id\/b7ed\/pemilu\/ppwp\/71\/06\/08\/20\/05\/7106082005009-20240215-062459--7f637ead-c3f2-4de5-a17b-a64a2ac26763.jpg","https:\/\/sirekap-obj-formc.kpu.go.id\/b7ed\/pemilu\/ppwp\/71\/06\/08\/20\/05\/7106082005009-20240215-062717--e1a35c67-c822-41cd-831f-7987e5e86f95.jpg","https:\/\/sirekap-obj-formc.kpu.go.id\/b7ed\/pemilu\/ppwp\/71\/06\/08\/20\/05\/7106082005009-20240215-062859--ef506011-f422-445d-9d22-c57cdd0433b2.jpg"],"administrasi":{"suara_sah":209,"suara_total":215,"pemilih_dpt_j":268,"pemilih_dpt_l":134,"pemilih_dpt_p":134,"pengguna_dpt_j":215,"pengguna_dpt_l":105,"pengguna_dpt_p":110,"pengguna_dptb_j":0,"pengguna_dptb_l":0,"pengguna_dptb_p":0,"suara_tidak_sah":6,"pengguna_total_j":215,"pengguna_total_l":105,"pengguna_total_p":110,"pengguna_non_dpt_j":0,"pengguna_non_dpt_l":0,"pengguna_non_dpt_p":0},"psu":null,"ts":"2024-02-15 15:00:29","status_suara":true,"status_adm":true}},"7106082001001":{"kode_prov":"71","kode_kab":"7106","kode_kec":"710608","kode_kel":"7106082001","kode_tps":"7106082001001","data_tps":{"chart":{"null":null,"100025":6,"100026":141,"100027":69},"images":["https:\/\/sirekap-obj-formc.kpu.go.id\/a725\/pemilu\/ppwp\/71\/06\/08\/20\/01\/7106082001001-20240214-185559--35b3d46d-122a-4a35-b26a-05ed599661f9.jpg","https:\/\/sirekap-obj-formc.kpu.go.id\/a725\/pemilu\/ppwp\/71\/06\/08\/20\/01\/7106082001001-20240214-184851--7bf28778-41a2-4bd3-9798-6c810b2d9ca9.jpg","https:\/\/sirekap-obj-formc.kpu.go.id\/a725\/pemilu\/ppwp\/71\/06\/08\/20\/01\/7106082001001-20240214-184813--21d0b6ad-8ab6-4a9a-89d1-7815ae6f811a.jpg"],"administrasi":{"suara_sah":216,"suara_total":216,"pemilih_dpt_j":242,"pemilih_dpt_l":120,"pemilih_dpt_p":122,"pengguna_dpt_j":210,"pengguna_dpt_l":103,"pengguna_dpt_p":107,"pengguna_dptb_j":5,"pengguna_dptb_l":3,"pengguna_dptb_p":2,"suara_tidak_sah":0,"pengguna_total_j":216,"pengguna_total_l":106,"pengguna_total_p":110,"pengguna_non_dpt_j":1,"pengguna_non_dpt_l":0,"pengguna_non_dpt_p":1},"psu":null,"ts":"2024-02-15 19:00:26","status_suara":true,"status_adm":true}},"7106082001002":{"kode_prov":"71","kode_kab":"7106","kode_kec":"710608","kode_kel":"7106082001","kode_tps":"7106082001002","data_tps":{"chart":{"null":null,"100025":5,"100026":124,"100027":74},"images":["https:\/\/sirekap-obj-formc.kpu.go.id\/5023\/pemilu\/ppwp\/71\/06\/08\/20\/01\/7106082001002-20240215-023546--3b8a06c9-6b3e-4290-aff8-52d207aa1f02.jpg","https:\/\/sirekap-obj-formc.kpu.go.id\/5023\/pemilu\/ppwp\/71\/06\/08\/20\/01\/7106082001002-20240215-023621--0c2d3f80-13e0-4384-b6b3-91e34fe9b822.jpg","https:\/\/sirekap-obj-formc.kpu.go.id\/5023\/pemilu\/ppwp\/71\/06\/08\/20\/01\/7106082001002-20240215-023714--c42fc3c1-d7d0-40d4-82b3-6654e46ff80b.jpg"],"administrasi":{"suara_sah":202,"suara_total":203,"pemilih_dpt_j":240,"pemilih_dpt_l":125,"pemilih_dpt_p":115,"pengguna_dpt_j":192,"pengguna_dpt_l":92,"pengguna_dpt_p":100,"pengguna_dptb_j":8,"pengguna_dptb_l":2,"pengguna_dptb_p":6,"suara_tidak_sah":1,"pengguna_total_j":203,"pengguna_total_l":95,"pengguna_total_p":108,"pengguna_non_dpt_j":3,"pengguna_non_dpt_l":1,"pengguna_non_dpt_p":2},"psu":null,"ts":"2024-02-15 12:00:28","status_suara":true,"status_adm":true}},"7106082001003":{"kode_prov":"71","kode_kab":"7106","kode_kec":"710608","kode_kel":"7106082001","kode_tps":"7106082001003","data_tps":{"mode":"hhcw","chart":{"null":null,"100025":5,"100026":125,"100027":71},"images":["https:\/\/sirekap-obj-formc.kpu.go.id\/920a\/pemilu\/ppwp\/71\/06\/08\/20\/01\/7106082001003-20240217-122110--5567c5f8-00ab-49d4-9c16-94b03fb48da4.jpg","https:\/\/sirekap-obj-formc.kpu.go.id\/920a\/pemilu\/ppwp\/71\/06\/08\/20\/01\/7106082001003-20240217-122640--f40be7b1-e133-4949-8c9b-7dc7b8077619.jpg","https:\/\/sirekap-obj-formc.kpu.go.id\/920a\/pemilu\/ppwp\/71\/06\/08\/20\/01\/7106082001003-20240217-123136--97f35fe1-cdea-4ba8-bbfc-368f7457dad7.jpg"],"administrasi":{"suara_sah":201,"suara_total":202,"pemilih_dpt_j":241,"pemilih_dpt_l":114,"pemilih_dpt_p":127,"pengguna_dpt_j":202,"pengguna_dpt_l":93,"pengguna_dpt_p":109,"pengguna_dptb_j":0,"pengguna_dptb_l":0,"pengguna_dptb_p":0,"suara_tidak_sah":1,"pengguna_total_j":202,"pengguna_total_l":93,"pengguna_total_p":109,"pengguna_non_dpt_j":0,"pengguna_non_dpt_l":0,"pengguna_non_dpt_p":0},"psu":null,"ts":"2024-02-17 13:37:34","status_suara":true,"status_adm":true}},"7106082001004":{"kode_prov":"71","kode_kab":"7106","kode_kec":"710608","kode_kel":"7106082001","kode_tps":"7106082001004","data_tps":{"mode":"hhcw","chart":{"null":null,"100025":6,"100026":127,"100027":74},"images":["https:\/\/sirekap-obj-formc.kpu.go.id\/1e61\/pemilu\/ppwp\/71\/06\/08\/20\/01\/7106082001004-20240217-121343--32b29878-213a-498e-a3d7-798288c0cc29.jpg","https:\/\/sirekap-obj-formc.kpu.go.id\/1e61\/pemilu\/ppwp\/71\/06\/08\/20\/01\/7106082001004-20240217-121654--14e04c7d-8cbc-4831-8f56-4347ccdce219.jpg","https:\/\/sirekap-obj-formc.kpu.go.id\/1e61\/pemilu\/ppwp\/71\/06\/08\/20\/01\/7106082001004-20240217-121827--81bbe4a3-b243-4074-b2c6-fe867be0bd1d.jpg"],"administrasi":{"suara_sah":207,"suara_total":208,"pemilih_dpt_j":244,"pemilih_dpt_l":125,"pemilih_dpt_p":119,"pengguna_dpt_j":208,"pengguna_dpt_l":107,"pengguna_dpt_p":101,"pengguna_dptb_j":0,"pengguna_dptb_l":0,"pengguna_dptb_p":0,"suara_tidak_sah":1,"pengguna_total_j":208,"pengguna_total_l":107,"pengguna_total_p":101,"pengguna_non_dpt_j":0,"pengguna_non_dpt_l":0,"pengguna_non_dpt_p":0},"psu":null,"ts":"2024-02-17 13:37:34","status_suara":true,"status_adm":true}},"7106082001005":{"kode_prov":"71","kode_kab":"7106","kode_kec":"710608","kode_kel":"7106082001","kode_tps":"7106082001005","data_tps":{"mode":"hhcw","chart":{"null":null,"100025":3,"100026":115,"100027":79},"images":["https:\/\/sirekap-obj-formc.kpu.go.id\/2879\/pemilu\/ppwp\/71\/06\/08\/20\/01\/7106082001005-20240223-173928--6a3c9faf-b1c2-4d94-95b0-573a86d7153e.jpg","https:\/\/sirekap-obj-formc.kpu.go.id\/2879\/pemilu\/ppwp\/71\/06\/08\/20\/01\/7106082001005-20240223-173956--c2f1f098-cae2-4fd6-bc2a-514b9073503f.jpg","https:\/\/sirekap-obj-formc.kpu.go.id\/2879\/pemilu\/ppwp\/71\/06\/08\/20\/01\/7106082001005-20240223-174041--33ae6d6e-2540-4d74-9468-165a9e51aac0.jpg"],"administrasi":null,"psu":null,"ts":"2024-02-24 22:31:28","status_suara":true,"status_adm":false}},"7106082001006":{"kode_prov":"71","kode_kab":"7106","kode_kec":"710608","kode_kel":"7106082001","kode_tps":"7106082001006","data_tps":{"mode":"hhcw","chart":{"null":null,"100025":0,"100026":107,"100027":88},"images":["https:\/\/sirekap-obj-formc.kpu.go.id\/0086\/pemilu\/ppwp\/71\/06\/08\/20\/01\/7106082001006-20240214-155826--b66fe221-6eae-4c56-8d94-91165df0757e.jpg","https:\/\/sirekap-obj-formc.kpu.go.id\/0086\/pemilu\/ppwp\/71\/06\/08\/20\/01\/7106082001006-20240223-180814--b022a1ea-a245-4ce9-84d0-ace57342d111.jpg","https:\/\/sirekap-obj-formc.kpu.go.id\/0086\/pemilu\/ppwp\/71\/06\/08\/20\/01\/7106082001006-20240218-181024--1848ec57-7cde-41b6-b2ad-552482333728.jpg"],"administrasi":{"suara_sah":195,"suara_total":197,"pemilih_dpt_j":241,"pemilih_dpt_l":110,"pemilih_dpt_p":131,"pengguna_dpt_j":196,"pengguna_dpt_l":85,"pengguna_dpt_p":111,"pengguna_dptb_j":0,"pengguna_dptb_l":0,"pengguna_dptb_p":0,"suara_tidak_sah":2,"pengguna_total_j":197,"pengguna_total_l":85,"pengguna_total_p":112,"pengguna_non_dpt_j":1,"pengguna_non_dpt_l":0,"pengguna_non_dpt_p":1},"psu":null,"ts":"2024-02-24 22:31:28","status_suara":true,"status_adm":true}},"7106082007001":{"kode_prov":"71","kode_kab":"7106","kode_kec":"710608","kode_kel":"7106082007","kode_tps":"7106082007001","data_tps":{"chart":{"null":null,"100025":0,"100026":185,"100027":49},"images":["https:\/\/sirekap-obj-formc.kpu.go.id\/140e\/pemilu\/ppwp\/71\/06\/08\/20\/07\/7106082007001-20240215-104309--fcf6cf53-2e98-4fe5-b950-81699eee8aa4.jpg","https:\/\/sirekap-obj-formc.kpu.go.id\/140e\/pemilu\/ppwp\/71\/06\/08\/20\/07\/7106082007001-20240215-104039--a9f7c434-49c3-4465-9be9-c20457b9aaf7.jpg","https:\/\/sirekap-obj-formc.kpu.go.id\/140e\/pemilu\/ppwp\/71\/06\/08\/20\/07\/7106082007001-20240215-104147--dffdf648-c63d-4d1d-951b-511810edad5d.jpg"],"administrasi":{"suara_sah":234,"suara_total":236,"pemilih_dpt_j":281,"pemilih_dpt_l":133,"pemilih_dpt_p":148,"pengguna_dpt_j":235,"pengguna_dpt_l":114,"pengguna_dpt_p":121,"pengguna_dptb_j":0,"pengguna_dptb_l":0,"pengguna_dptb_p":0,"suara_tidak_sah":2,"pengguna_total_j":236,"pengguna_total_l":114,"pengguna_total_p":122,"pengguna_non_dpt_j":1,"pengguna_non_dpt_l":0,"pengguna_non_dpt_p":1},"psu":null,"ts":"2024-02-15 20:30:46","status_suara":true,"status_adm":true}},"7106082007002":{"kode_prov":"71","kode_kab":"7106","kode_kec":"710608","kode_kel":"7106082007","kode_tps":"7106082007002","data_tps":{"chart":{"null":null,"100025":27,"100026":147,"100027":34},"images":["https:\/\/sirekap-obj-formc.kpu.go.id\/4ca0\/pemilu\/ppwp\/71\/06\/08\/20\/07\/7106082007002-20240215-044406--f123a96a-9b98-4b8c-8b58-6e8a348b285c.jpg","https:\/\/sirekap-obj-formc.kpu.go.id\/4ca0\/pemilu\/ppwp\/71\/06\/08\/20\/07\/7106082007002-20240215-044846--1af497e5-4c2b-41a2-b25f-96ef676b5efa.jpg","https:\/\/sirekap-obj-formc.kpu.go.id\/4ca0\/pemilu\/ppwp\/71\/06\/08\/20\/07\/7106082007002-20240215-044916--942d09ec-96c3-4211-802e-1c8ac6a9c0d4.jpg"],"administrasi":{"suara_sah":208,"suara_total":211,"pemilih_dpt_j":270,"pemilih_dpt_l":123,"pemilih_dpt_p":147,"pengguna_dpt_j":211,"pengguna_dpt_l":99,"pengguna_dpt_p":112,"pengguna_dptb_j":0,"pengguna_dptb_l":0,"pengguna_dptb_p":0,"suara_tidak_sah":3,"pengguna_total_j":211,"pengguna_total_l":0,"pengguna_total_p":0,"pengguna_non_dpt_j":0,"pengguna_non_dpt_l":0,"pengguna_non_dpt_p":0},"psu":null,"ts":"2024-02-15 22:30:27","status_suara":true,"status_adm":true}},"7106082007003":{"kode_prov":"71","kode_kab":"7106","kode_kec":"710608","kode_kel":"7106082007","kode_tps":"7106082007003","data_tps":{"mode":"hhcw","chart":{"null":null,"100025":7,"100026":176,"100027":43},"images":["https:\/\/sirekap-obj-formc.kpu.go.id\/1303\/pemilu\/ppwp\/71\/06\/08\/20\/07\/7106082007003-20240220-214021--ca2ee645-56bd-4661-a27c-301e4502d3ea.jpg","https:\/\/sirekap-obj-formc.kpu.go.id\/1303\/pemilu\/ppwp\/71\/06\/08\/20\/07\/7106082007003-20240220-214126--ce5682ff-4d21-468b-af6d-3c23cf776818.jpg","https:\/\/sirekap-obj-formc.kpu.go.id\/1303\/pemilu\/ppwp\/71\/06\/08\/20\/07\/7106082007003-20240220-214245--b4b94be9-7923-473f-81db-d624e54c0cde.jpg"],"administrasi":{"suara_sah":226,"suara_total":227,"pemilih_dpt_j":267,"pemilih_dpt_l":130,"pemilih_dpt_p":137,"pengguna_dpt_j":219,"pengguna_dpt_l":104,"pengguna_dpt_p":115,"pengguna_dptb_j":6,"pengguna_dptb_l":3,"pengguna_dptb_p":3,"suara_tidak_sah":1,"pengguna_total_j":227,"pengguna_total_l":108,"pengguna_total_p":119,"pengguna_non_dpt_j":2,"pengguna_non_dpt_l":1,"pengguna_non_dpt_p":1},"psu":null,"ts":"2024-02-24 22:31:28","status_suara":true,"status_adm":true}},"7106082007004":{"kode_prov":"71","kode_kab":"7106","kode_kec":"710608","kode_kel":"7106082007","kode_tps":"7106082007004","data_tps":{"mode":"hhcw","chart":{"null":null,"100025":3,"100026":179,"100027":97},"images":["https:\/\/sirekap-obj-formc.kpu.go.id\/c441\/pemilu\/ppwp\/71\/06\/08\/20\/07\/7106082007004-20240218-140201--b6622328-7327-421a-93f2-fe9a9d6d645b.jpg","https:\/\/sirekap-obj-formc.kpu.go.id\/c441\/pemilu\/ppwp\/71\/06\/08\/20\/07\/7106082007004-20240218-140344--58c11bba-b613-4e3a-bedc-b89f8df7939f.jpg","https:\/\/sirekap-obj-formc.kpu.go.id\/c441\/pemilu\/ppwp\/71\/06\/08\/20\/07\/7106082007004-20240218-140439--824ed607-34fc-459f-81fa-1878330fd185.jpg"],"administrasi":{"suara_sah":229,"suara_total":232,"pemilih_dpt_j":276,"pemilih_dpt_l":136,"pemilih_dpt_p":140,"pengguna_dpt_j":229,"pengguna_dpt_l":110,"pengguna_dpt_p":119,"pengguna_dptb_j":0,"pengguna_dptb_l":0,"pengguna_dptb_p":0,"suara_tidak_sah":3,"pengguna_total_j":232,"pengguna_total_l":111,"pengguna_total_p":121,"pengguna_non_dpt_j":3,"pengguna_non_dpt_l":1,"pengguna_non_dpt_p":2},"psu":null,"ts":"2024-02-19 06:16:00","status_suara":true,"status_adm":true}},"7106082007005":{"kode_prov":"71","kode_kab":"7106","kode_kec":"710608","kode_kel":"7106082007","kode_tps":"7106082007005","data_tps":{"mode":"hhcw","chart":{"null":null,"100025":13,"100026":139,"100027":74},"images":["https:\/\/sirekap-obj-formc.kpu.go.id\/9bbf\/pemilu\/ppwp\/71\/06\/08\/20\/07\/7106082007005-20240223-091034--ec0a0cca-be17-4548-b455-f9fcba337185.jpg","https:\/\/sirekap-obj-formc.kpu.go.id\/9bbf\/pemilu\/ppwp\/71\/06\/08\/20\/07\/7106082007005-20240223-091117--b1cea637-6c95-484e-bdea-bc5d85958004.jpg","https:\/\/sirekap-obj-formc.kpu.go.id\/9bbf\/pemilu\/ppwp\/71\/06\/08\/20\/07\/7106082007005-20240223-091209--5f219ef8-c35a-4888-a695-5e6efd54e12f.jpg"],"administrasi":{"suara_sah":226,"suara_total":227,"pemilih_dpt_j":279,"pemilih_dpt_l":134,"pemilih_dpt_p":145,"pengguna_dpt_j":212,"pengguna_dpt_l":99,"pengguna_dpt_p":113,"pengguna_dptb_j":9,"pengguna_dptb_l":5,"pengguna_dptb_p":4,"suara_tidak_sah":1,"pengguna_total_j":227,"pengguna_total_l":108,"pengguna_total_p":119,"pengguna_non_dpt_j":6,"pengguna_non_dpt_l":4,"pengguna_non_dpt_p":2},"psu":null,"ts":"2024-02-24 22:31:28","status_suara":true,"status_adm":true}},"7106082007006":{"kode_prov":"71","kode_kab":"7106","kode_kec":"710608","kode_kel":"7106082007","kode_tps":"7106082007006","data_tps":{"mode":"hhcw","chart":{"null":null,"100025":11,"100026":162,"100027":27},"images":["https:\/\/sirekap-obj-formc.kpu.go.id\/0ffd\/pemilu\/ppwp\/71\/06\/08\/20\/07\/7106082007006-20240223-114139--0c4b18a1-2a97-4e1b-a18c-3acf2087eb40.jpg","https:\/\/sirekap-obj-formc.kpu.go.id\/0ffd\/pemilu\/ppwp\/71\/06\/08\/20\/07\/7106082007006-20240223-114243--baf33e70-8d02-4907-9a77-c4bb5d94e39d.jpg","https:\/\/sirekap-obj-formc.kpu.go.id\/0ffd\/pemilu\/ppwp\/71\/06\/08\/20\/07\/7106082007006-20240223-114342--99d81cb2-b776-40f8-ab53-245b854aa614.jpg"],"administrasi":{"suara_sah":200,"suara_total":202,"pemilih_dpt_j":257,"pemilih_dpt_l":131,"pemilih_dpt_p":126,"pengguna_dpt_j":199,"pengguna_dpt_l":97,"pengguna_dpt_p":102,"pengguna_dptb_j":0,"pengguna_dptb_l":0,"pengguna_dptb_p":0,"suara_tidak_sah":2,"pengguna_total_j":202,"pengguna_total_l":99,"pengguna_total_p":103,"pengguna_non_dpt_j":3,"pengguna_non_dpt_l":2,"pengguna_non_dpt_p":1},"psu":null,"ts":"2024-02-24 22:31:28","status_suara":true,"status_adm":true}},"7106082007007":{"kode_prov":"71","kode_kab":"7106","kode_kec":"710608","kode_kel":"7106082007","kode_tps":"7106082007007","data_tps":{"mode":"hhcw","chart":{"null":null,"100025":3,"100026":200,"100027":31},"images":["https:\/\/sirekap-obj-formc.kpu.go.id\/5834\/pemilu\/ppwp\/71\/06\/08\/20\/07\/7106082007007-20240223-144110--97202375-6a18-45ca-b94d-d7a4dd2e0c3c.jpg","https:\/\/sirekap-obj-formc.kpu.go.id\/5834\/pemilu\/ppwp\/71\/06\/08\/20\/07\/7106082007007-20240223-144223--4297767d-b599-46bd-bbdc-dc4bc777ca4b.jpg","https:\/\/sirekap-obj-formc.kpu.go.id\/5834\/pemilu\/ppwp\/71\/06\/08\/20\/07\/7106082007007-20240223-144334--95aeba95-fa85-4a76-80f2-760c56ddddb2.jpg"],"administrasi":{"suara_sah":234,"suara_total":236,"pemilih_dpt_j":269,"pemilih_dpt_l":134,"pemilih_dpt_p":135,"pengguna_dpt_j":232,"pengguna_dpt_l":115,"pengguna_dpt_p":117,"pengguna_dptb_j":1,"pengguna_dptb_l":1,"pengguna_dptb_p":0,"suara_tidak_sah":2,"pengguna_total_j":236,"pengguna_total_l":116,"pengguna_total_p":120,"pengguna_non_dpt_j":3,"pengguna_non_dpt_l":0,"pengguna_non_dpt_p":3},"psu":null,"ts":"2024-02-24 22:31:28","status_suara":true,"status_adm":true}},"7106082007008":{"kode_prov":"71","kode_kab":"7106","kode_kec":"710608","kode_kel":"7106082007","kode_tps":"7106082007008","data_tps":{"mode":"hhcw","chart":{"null":null,"100025":39,"100026":179,"100027":24},"images":["https:\/\/sirekap-obj-formc.kpu.go.id\/ff2f\/pemilu\/ppwp\/71\/06\/08\/20\/07\/7106082007008-20240223-181225--66b27aac-14ab-4503-b956-98196e0d67a7.jpg","https:\/\/sirekap-obj-formc.kpu.go.id\/ff2f\/pemilu\/ppwp\/71\/06\/08\/20\/07\/7106082007008-20240223-181249--c723de73-ba4f-4217-b5e2-44701146d57b.jpg","https:\/\/sirekap-obj-formc.kpu.go.id\/ff2f\/pemilu\/ppwp\/71\/06\/08\/20\/07\/7106082007008-20240223-181322--29bfc956-b670-4f99-bc47-f5c7ec47f110.jpg"],"administrasi":null,"psu":null,"ts":"2024-02-24 22:31:28","status_suara":true,"status_adm":false}},"7106082007009":{"kode_prov":"71","kode_kab":"7106","kode_kec":"710608","kode_kel":"7106082007","kode_tps":"7106082007009","data_tps":{"chart":{"null":null,"100025":12,"100026":172,"100027":20},"images":["https:\/\/sirekap-obj-formc.kpu.go.id\/7964\/pemilu\/ppwp\/71\/06\/08\/20\/07\/7106082007009-20240214-222743--c3eb2775-7a23-4ecd-aeb1-bad85a1b0b91.jpg","https:\/\/sirekap-obj-formc.kpu.go.id\/7964\/pemilu\/ppwp\/71\/06\/08\/20\/07\/7106082007009-20240215-001058--45ff71a0-82e4-4431-be6c-8c857db44d3a.jpg","https:\/\/sirekap-obj-formc.kpu.go.id\/7964\/pemilu\/ppwp\/71\/06\/08\/20\/07\/7106082007009-20240215-001220--e4d374f0-c45d-471c-ad25-5bd360e2a63d.jpg"],"administrasi":{"suara_sah":204,"suara_total":209,"pemilih_dpt_j":251,"pemilih_dpt_l":123,"pemilih_dpt_p":128,"pengguna_dpt_j":204,"pengguna_dpt_l":95,"pengguna_dpt_p":109,"pengguna_dptb_j":0,"pengguna_dptb_l":0,"pengguna_dptb_p":0,"suara_tidak_sah":5,"pengguna_total_j":209,"pengguna_total_l":97,"pengguna_total_p":112,"pengguna_non_dpt_j":5,"pengguna_non_dpt_l":2,"pengguna_non_dpt_p":3},"psu":null,"ts":"2024-02-15 20:30:46","status_suara":true,"status_adm":true}},"7106082007010":{"kode_prov":"71","kode_kab":"7106","kode_kec":"710608","kode_kel":"7106082007","kode_tps":"7106082007010","data_tps":{"chart":{"null":null,"100025":4,"100026":204,"100027":22},"images":["https:\/\/sirekap-obj-formc.kpu.go.id\/83ed\/pemilu\/ppwp\/71\/06\/08\/20\/07\/7106082007010-20240214-185006--9fc407c3-071b-40b7-833c-77c018fa7049.jpg","https:\/\/sirekap-obj-formc.kpu.go.id\/83ed\/pemilu\/ppwp\/71\/06\/08\/20\/07\/7106082007010-20240214-190238--f501a9cf-238d-457d-8394-7799d05ac6f6.jpg","https:\/\/sirekap-obj-formc.kpu.go.id\/83ed\/pemilu\/ppwp\/71\/06\/08\/20\/07\/7106082007010-20240214-190819--b69933d2-ca54-4ff8-99dc-0f23b0e287d0.jpg"],"administrasi":{"suara_sah":230,"suara_total":231,"pemilih_dpt_j":250,"pemilih_dpt_l":120,"pemilih_dpt_p":130,"pengguna_dpt_j":216,"pengguna_dpt_l":102,"pengguna_dpt_p":114,"pengguna_dptb_j":4,"pengguna_dptb_l":3,"pengguna_dptb_p":1,"suara_tidak_sah":1,"pengguna_total_j":231,"pengguna_total_l":109,"pengguna_total_p":122,"pengguna_non_dpt_j":11,"pengguna_non_dpt_l":4,"pengguna_non_dpt_p":7},"psu":null,"ts":"2024-02-14 21:46:01","status_suara":true,"status_adm":true}},"7106082007011":{"kode_prov":"71","kode_kab":"7106","kode_kec":"710608","kode_kel":"7106082007","kode_tps":"7106082007011","data_tps":{"mode":"hhcw","chart":{"null":null,"100025":7,"100026":168,"100027":20},"images":["https:\/\/sirekap-obj-formc.kpu.go.id\/a135\/pemilu\/ppwp\/71\/06\/08\/20\/07\/7106082007011-20240218-134808--5c27dbf9-7c00-476f-b96e-5b499a22748d.jpg","https:\/\/sirekap-obj-formc.kpu.go.id\/a135\/pemilu\/ppwp\/71\/06\/08\/20\/07\/7106082007011-20240218-133754--62377b6d-81b8-4976-88b9-80d9cf9094b2.jpg","https:\/\/sirekap-obj-formc.kpu.go.id\/a135\/pemilu\/ppwp\/71\/06\/08\/20\/07\/7106082007011-20240218-133634--ccfd2496-5d58-4ba8-b1bc-c9afe98c29ff.jpg"],"administrasi":{"suara_sah":195,"suara_total":195,"pemilih_dpt_j":195,"pemilih_dpt_l":92,"pemilih_dpt_p":103,"pengguna_dpt_j":186,"pengguna_dpt_l":89,"pengguna_dpt_p":97,"pengguna_dptb_j":1,"pengguna_dptb_l":0,"pengguna_dptb_p":1,"suara_tidak_sah":0,"pengguna_total_j":195,"pengguna_total_l":92,"pengguna_total_p":103,"pengguna_non_dpt_j":8,"pengguna_non_dpt_l":3,"pengguna_non_dpt_p":5},"psu":null,"ts":"2024-02-19 06:16:00","status_suara":true,"status_adm":true}},"7106082007012":{"kode_prov":"71","kode_kab":"7106","kode_kec":"710608","kode_kel":"7106082007","kode_tps":"7106082007012","data_tps":{"mode":"hhcw","chart":{"null":null,"100025":8,"100026":107,"100027":11},"images":["https:\/\/sirekap-obj-formc.kpu.go.id\/66b3\/pemilu\/ppwp\/71\/06\/08\/20\/07\/7106082007012-20240218-211352--912f323c-5dd6-40b9-b3c2-11d209e35110.jpg","https:\/\/sirekap-obj-formc.kpu.go.id\/66b3\/pemilu\/ppwp\/71\/06\/08\/20\/07\/7106082007012-20240214-230522--f1a4359f-eed2-40dc-a2ef-4f16e9db9220.jpg","https:\/\/sirekap-obj-formc.kpu.go.id\/66b3\/pemilu\/ppwp\/71\/06\/08\/20\/07\/7106082007012-20240218-210735--50b2be4b-9160-49da-a7c3-370974a53e44.jpg"],"administrasi":{"suara_sah":126,"suara_total":127,"pemilih_dpt_j":185,"pemilih_dpt_l":100,"pemilih_dpt_p":85,"pengguna_dpt_j":111,"pengguna_dpt_l":58,"pengguna_dpt_p":53,"pengguna_dptb_j":2,"pengguna_dptb_l":0,"pengguna_dptb_p":2,"suara_tidak_sah":1,"pengguna_total_j":127,"pengguna_total_l":63,"pengguna_total_p":64,"pengguna_non_dpt_j":14,"pengguna_non_dpt_l":5,"pengguna_non_dpt_p":9},"psu":null,"ts":"2024-02-19 06:16:00","status_suara":true,"status_adm":true}},"7106082011001":{"kode_prov":"71","kode_kab":"7106","kode_kec":"710608","kode_kel":"7106082011","kode_tps":"7106082011001","data_tps":{"mode":"hhcw","chart":{"null":null,"100025":19,"100026":199,"100027":6},"images":["https:\/\/sirekap-obj-formc.kpu.go.id\/9aa3\/pemilu\/ppwp\/71\/06\/08\/20\/11\/7106082011001-20240224-165640--baf8cb55-3fea-4bf1-ae85-544bd0017625.jpg","https:\/\/sirekap-obj-formc.kpu.go.id\/9aa3\/pemilu\/ppwp\/71\/06\/08\/20\/11\/7106082011001-20240224-165522--fe31b927-2acd-48bf-9614-66a108b1c66c.jpg","https:\/\/sirekap-obj-formc.kpu.go.id\/9aa3\/pemilu\/ppwp\/71\/06\/08\/20\/11\/7106082011001-20240224-165606--6b247227-eb97-4f2b-bb2b-8fb4643b1507.jpg"],"administrasi":null,"psu":null,"ts":"2024-02-24 22:31:28","status_suara":true,"status_adm":false}},"7106082011002":{"kode_prov":"71","kode_kab":"7106","kode_kec":"710608","kode_kel":"7106082011","kode_tps":"7106082011002","data_tps":{"mode":"hhcw","chart":{"null":null,"100025":12,"100026":175,"100027":28},"images":["https:\/\/sirekap-obj-formc.kpu.go.id\/540c\/pemilu\/ppwp\/71\/06\/08\/20\/11\/7106082011002-20240217-181520--5ca6a263-805c-4b79-9ff0-50ccf6bc7431.jpg","https:\/\/sirekap-obj-formc.kpu.go.id\/540c\/pemilu\/ppwp\/71\/06\/08\/20\/11\/7106082011002-20240217-181402--9b904d5a-6d3a-4b78-a1c4-5cd367f71b45.jpg","https:\/\/sirekap-obj-formc.kpu.go.id\/540c\/pemilu\/ppwp\/71\/06\/08\/20\/11\/7106082011002-20240217-181210--f4019f1c-fe75-4145-ace2-ca5a22147d4a.jpg"],"administrasi":{"suara_sah":215,"suara_total":216,"pemilih_dpt_j":252,"pemilih_dpt_l":122,"pemilih_dpt_p":130,"pengguna_dpt_j":207,"pengguna_dpt_l":97,"pengguna_dpt_p":110,"pengguna_dptb_j":7,"pengguna_dptb_l":5,"pengguna_dptb_p":2,"suara_tidak_sah":1,"pengguna_total_j":216,"pengguna_total_l":102,"pengguna_total_p":114,"pengguna_non_dpt_j":2,"pengguna_non_dpt_l":0,"pengguna_non_dpt_p":2},"psu":null,"ts":"2024-02-19 06:16:00","status_suara":true,"status_adm":true}},"7106082011003":{"kode_prov":"71","kode_kab":"7106","kode_kec":"710608","kode_kel":"7106082011","kode_tps":"7106082011003","data_tps":{"mode":"hhcw","chart":{"null":null,"100025":2,"100026":187,"100027":31},"images":["https:\/\/sirekap-obj-formc.kpu.go.id\/0b1d\/pemilu\/ppwp\/71\/06\/08\/20\/11\/7106082011003-20240217-181909--02383fa3-373d-4cdc-8be5-92cfd2440e13.jpg","https:\/\/sirekap-obj-formc.kpu.go.id\/0b1d\/pemilu\/ppwp\/71\/06\/08\/20\/11\/7106082011003-20240217-195831--9fc1690e-ad7d-49f1-af52-9b57e5b86815.jpg","https:\/\/sirekap-obj-formc.kpu.go.id\/0b1d\/pemilu\/ppwp\/71\/06\/08\/20\/11\/7106082011003-20240217-195956--dce80d74-000b-40b2-9077-558e768014f7.jpg"],"administrasi":{"suara_sah":220,"suara_total":22,"pemilih_dpt_j":245,"pemilih_dpt_l":103,"pemilih_dpt_p":142,"pengguna_dpt_j":211,"pengguna_dpt_l":87,"pengguna_dpt_p":124,"pengguna_dptb_j":3,"pengguna_dptb_l":1,"pengguna_dptb_p":2,"suara_tidak_sah":2,"pengguna_total_j":222,"pengguna_total_l":90,"pengguna_total_p":132,"pengguna_non_dpt_j":8,"pengguna_non_dpt_l":2,"pengguna_non_dpt_p":6},"psu":null,"ts":"2024-02-19 06:16:00","status_suara":true,"status_adm":true}},"7106082011004":{"kode_prov":"71","kode_kab":"7106","kode_kec":"710608","kode_kel":"7106082011","kode_tps":"7106082011004","data_tps":{"chart":{"null":null,"100025":10,"100026":199,"100027":35},"images":["https:\/\/sirekap-obj-formc.kpu.go.id\/3556\/pemilu\/ppwp\/71\/06\/08\/20\/11\/7106082011004-20240214-202353--03b38fe8-0359-4ef1-bbcd-40c558c4ded6.jpg","https:\/\/sirekap-obj-formc.kpu.go.id\/3556\/pemilu\/ppwp\/71\/06\/08\/20\/11\/7106082011004-20240214-201959--ff16169c-609e-407b-96d7-620dce049681.jpg","https:\/\/sirekap-obj-formc.kpu.go.id\/3556\/pemilu\/ppwp\/71\/06\/08\/20\/11\/7106082011004-20240214-203754--939d2161-2e83-4903-be19-70585638cc77.jpg"],"administrasi":{"suara_sah":244,"suara_total":245,"pemilih_dpt_j":260,"pemilih_dpt_l":129,"pemilih_dpt_p":131,"pengguna_dpt_j":226,"pengguna_dpt_l":106,"pengguna_dpt_p":120,"pengguna_dptb_j":9,"pengguna_dptb_l":4,"pengguna_dptb_p":5,"suara_tidak_sah":1,"pengguna_total_j":245,"pengguna_total_l":113,"pengguna_total_p":128,"pengguna_non_dpt_j":10,"pengguna_non_dpt_l":3,"pengguna_non_dpt_p":7},"psu":null,"ts":"2024-02-15 20:00:44","status_suara":true,"status_adm":true}},"7106082011005":{"kode_prov":"71","kode_kab":"7106","kode_kec":"710608","kode_kel":"7106082011","kode_tps":"7106082011005","data_tps":{"mode":"hhcw","chart":{"null":null,"100025":5,"100026":157,"100027":35},"images":["https:\/\/sirekap-obj-formc.kpu.go.id\/6d02\/pemilu\/ppwp\/71\/06\/08\/20\/11\/7106082011005-20240225-101838--c4cae545-4be1-44c2-8f93-17b794154240.jpg","https:\/\/sirekap-obj-formc.kpu.go.id\/6d02\/pemilu\/ppwp\/71\/06\/08\/20\/11\/7106082011005-20240225-101947--d38fb317-361f-4c53-a78c-9483b28e97b5.jpg","https:\/\/sirekap-obj-formc.kpu.go.id\/6d02\/pemilu\/ppwp\/71\/06\/08\/20\/11\/7106082011005-20240225-101912--bb8eac04-e4a9-431e-9f95-dc7794e2f521.jpg"],"administrasi":null,"psu":null,"ts":"2024-02-26 00:00:00","status_suara":true,"status_adm":false}},"7106082011006":{"kode_prov":"71","kode_kab":"7106","kode_kec":"710608","kode_kel":"7106082011","kode_tps":"7106082011006","data_tps":{"mode":"hhcw","chart":{"null":null,"100025":1,"100026":179,"100027":26},"images":["https:\/\/sirekap-obj-formc.kpu.go.id\/32d6\/pemilu\/ppwp\/71\/06\/08\/20\/11\/7106082011006-20240217-173153--ceeb517c-230f-48fb-902f-4745fae2f19d.jpg","https:\/\/sirekap-obj-formc.kpu.go.id\/32d6\/pemilu\/ppwp\/71\/06\/08\/20\/11\/7106082011006-20240217-173417--e30824ca-7740-4f9d-8d23-9d50b17120c0.jpg","https:\/\/sirekap-obj-formc.kpu.go.id\/32d6\/pemilu\/ppwp\/71\/06\/08\/20\/11\/7106082011006-20240217-173036--e1fd3eea-3b00-404c-9f0e-9afedf5747ea.jpg"],"administrasi":{"suara_sah":206,"suara_total":206,"pemilih_dpt_j":244,"pemilih_dpt_l":114,"pemilih_dpt_p":130,"pengguna_dpt_j":194,"pengguna_dpt_l":92,"pengguna_dpt_p":102,"pengguna_dptb_j":2,"pengguna_dptb_l":1,"pengguna_dptb_p":1,"suara_tidak_sah":0,"pengguna_total_j":206,"pengguna_total_l":95,"pengguna_total_p":111,"pengguna_non_dpt_j":10,"pengguna_non_dpt_l":2,"pengguna_non_dpt_p":8},"psu":null,"ts":"2024-02-17 18:00:00","status_suara":true,"status_adm":true}},"7106082011007":{"kode_prov":"71","kode_kab":"7106","kode_kec":"710608","kode_kel":"7106082011","kode_tps":"7106082011007","data_tps":{"chart":{"null":null,"100025":3,"100026":179,"100027":26},"images":["https:\/\/sirekap-obj-formc.kpu.go.id\/9c47\/pemilu\/ppwp\/71\/06\/08\/20\/11\/7106082011007-20240214-224258--5c68ea1e-3e96-4083-a51a-a30248858701.jpg","https:\/\/sirekap-obj-formc.kpu.go.id\/9c47\/pemilu\/ppwp\/71\/06\/08\/20\/11\/7106082011007-20240215-081247--67ddadec-8b12-4862-a968-8e2537797436.jpg","https:\/\/sirekap-obj-formc.kpu.go.id\/9c47\/pemilu\/ppwp\/71\/06\/08\/20\/11\/7106082011007-20240215-081355--92f4f3bd-2dba-448f-af78-8fdcc14564b5.jpg"],"administrasi":null,"psu":null,"ts":"2024-02-15 17:00:25","status_suara":true,"status_adm":false}},"7106082011008":{"kode_prov":"71","kode_kab":"7106","kode_kec":"710608","kode_kel":"7106082011","kode_tps":"7106082011008","data_tps":{"chart":{"null":null,"100025":3,"100026":129,"100027":13},"images":[null,"https:\/\/sirekap-obj-formc.kpu.go.id\/d753\/pemilu\/ppwp\/71\/06\/08\/20\/11\/7106082011008-20240214-141736--add24f8d-d3b1-45c9-8e34-65d0f61c1efd.jpg","https:\/\/sirekap-obj-formc.kpu.go.id\/d753\/pemilu\/ppwp\/71\/06\/08\/20\/11\/7106082011008-20240214-141828--0c006431-7ca9-4af5-b24b-76b89179ed4b.jpg"],"administrasi":null,"psu":null,"ts":"2024-02-15 07:00:44","status_suara":true,"status_adm":false}},"7106082012001":{"kode_prov":"71","kode_kab":"7106","kode_kec":"710608","kode_kel":"7106082012","kode_tps":"7106082012001","data_tps":{"mode":"hhcw","chart":{"null":null,"100025":1,"100026":156,"100027":29},"images":["https:\/\/sirekap-obj-formc.kpu.go.id\/20be\/pemilu\/ppwp\/71\/06\/08\/20\/12\/7106082012001-20240218-204750--9a287ce8-e475-43ce-a9ec-3fe53927b0b0.jpg","https:\/\/sirekap-obj-formc.kpu.go.id\/20be\/pemilu\/ppwp\/71\/06\/08\/20\/12\/7106082012001-20240218-204811--a534156a-778e-4ab9-b739-e4b2810a7d62.jpg","https:\/\/sirekap-obj-formc.kpu.go.id\/20be\/pemilu\/ppwp\/71\/06\/08\/20\/12\/7106082012001-20240218-205402--bad409d6-ddca-47b9-9899-78e186869215.jpg"],"administrasi":{"suara_sah":186,"suara_total":186,"pemilih_dpt_j":222,"pemilih_dpt_l":102,"pemilih_dpt_p":120,"pengguna_dpt_j":184,"pengguna_dpt_l":83,"pengguna_dpt_p":101,"pengguna_dptb_j":0,"pengguna_dptb_l":0,"pengguna_dptb_p":0,"suara_tidak_sah":0,"pengguna_total_j":186,"pengguna_total_l":84,"pengguna_total_p":102,"pengguna_non_dpt_j":2,"pengguna_non_dpt_l":1,"pengguna_non_dpt_p":1},"psu":null,"ts":"2024-02-19 06:16:00","status_suara":true,"status_adm":true}},"7106082012002":{"kode_prov":"71","kode_kab":"7106","kode_kec":"710608","kode_kel":"7106082012","kode_tps":"7106082012002","data_tps":{"mode":"hhcw","chart":{"null":null,"100025":5,"100026":153,"100027":32},"images":["https:\/\/sirekap-obj-formc.kpu.go.id\/7168\/pemilu\/ppwp\/71\/06\/08\/20\/12\/7106082012002-20240223-121544--4e3091b4-96dc-4381-93be-2786f01387b5.jpg","https:\/\/sirekap-obj-formc.kpu.go.id\/7168\/pemilu\/ppwp\/71\/06\/08\/20\/12\/7106082012002-20240223-121752--c6ed1e50-50a2-4785-949f-1e45427d7e5f.jpg","https:\/\/sirekap-obj-formc.kpu.go.id\/7168\/pemilu\/ppwp\/71\/06\/08\/20\/12\/7106082012002-20240223-121845--6ec51217-a5e8-4a14-b3a8-0308fd7b9e62.jpg"],"administrasi":{"suara_sah":190,"suara_total":190,"pemilih_dpt_j":231,"pemilih_dpt_l":121,"pemilih_dpt_p":110,"pengguna_dpt_j":189,"pengguna_dpt_l":101,"pengguna_dpt_p":88,"pengguna_dptb_j":0,"pengguna_dptb_l":0,"pengguna_dptb_p":0,"suara_tidak_sah":0,"pengguna_total_j":190,"pengguna_total_l":102,"pengguna_total_p":88,"pengguna_non_dpt_j":1,"pengguna_non_dpt_l":1,"pengguna_non_dpt_p":0},"psu":null,"ts":"2024-02-24 22:31:28","status_suara":true,"status_adm":true}},"7106082012003":{"kode_prov":"71","kode_kab":"7106","kode_kec":"710608","kode_kel":"7106082012","kode_tps":"7106082012003","data_tps":{"chart":{"null":null,"100025":8,"100026":150,"100027":55},"images":["https:\/\/sirekap-obj-formc.kpu.go.id\/bd2d\/pemilu\/ppwp\/71\/06\/08\/20\/12\/7106082012003-20240214-230900--250f16bb-1ae3-48ce-b2da-385aa23cdcf2.jpg","https:\/\/sirekap-obj-formc.kpu.go.id\/bd2d\/pemilu\/ppwp\/71\/06\/08\/20\/12\/7106082012003-20240214-231414--621b0588-1351-42ae-a575-0e484852c7f9.jpg","https:\/\/sirekap-obj-formc.kpu.go.id\/bd2d\/pemilu\/ppwp\/71\/06\/08\/20\/12\/7106082012003-20240214-231851--af6324d0-dcd2-4113-bdf0-1c3f2b5e5281.jpg"],"administrasi":{"suara_sah":213,"suara_total":214,"pemilih_dpt_j":237,"pemilih_dpt_l":125,"pemilih_dpt_p":112,"pengguna_dpt_j":211,"pengguna_dpt_l":112,"pengguna_dpt_p":99,"pengguna_dptb_j":0,"pengguna_dptb_l":0,"pengguna_dptb_p":0,"suara_tidak_sah":1,"pengguna_total_j":214,"pengguna_total_l":115,"pengguna_total_p":99,"pengguna_non_dpt_j":3,"pengguna_non_dpt_l":3,"pengguna_non_dpt_p":0},"psu":null,"ts":"2024-02-15 18:30:25","status_suara":true,"status_adm":true}},"7106082012004":{"kode_prov":"71","kode_kab":"7106","kode_kec":"710608","kode_kel":"7106082012","kode_tps":"7106082012004","data_tps":{"chart":{"null":null,"100025":5,"100026":149,"100027":41},"images":["https:\/\/sirekap-obj-formc.kpu.go.id\/7b59\/pemilu\/ppwp\/71\/06\/08\/20\/12\/7106082012004-20240215-061702--8f79554f-e3bc-4340-b3d9-394fe117d447.jpg","https:\/\/sirekap-obj-formc.kpu.go.id\/7b59\/pemilu\/ppwp\/71\/06\/08\/20\/12\/7106082012004-20240215-061729--eef26ce1-ee58-4b21-a187-f4dfbb90dbe2.jpg","https:\/\/sirekap-obj-formc.kpu.go.id\/7b59\/pemilu\/ppwp\/71\/06\/08\/20\/12\/7106082012004-20240215-061754--1f5c9ca9-ff13-4fab-9a37-3118f2061292.jpg"],"administrasi":{"suara_sah":195,"suara_total":197,"pemilih_dpt_j":236,"pemilih_dpt_l":111,"pemilih_dpt_p":125,"pengguna_dpt_j":191,"pengguna_dpt_l":96,"pengguna_dpt_p":95,"pengguna_dptb_j":0,"pengguna_dptb_l":0,"pengguna_dptb_p":0,"suara_tidak_sah":2,"pengguna_total_j":197,"pengguna_total_l":100,"pengguna_total_p":97,"pengguna_non_dpt_j":6,"pengguna_non_dpt_l":4,"pengguna_non_dpt_p":2},"psu":null,"ts":"2024-02-15 22:30:27","status_suara":true,"status_adm":true}},"7106082012005":{"kode_prov":"71","kode_kab":"7106","kode_kec":"710608","kode_kel":"7106082012","kode_tps":"7106082012005","data_tps":{"chart":{"null":null,"100025":9,"100026":129,"100027":34},"images":["https:\/\/sirekap-obj-formc.kpu.go.id\/053f\/pemilu\/ppwp\/71\/06\/08\/20\/12\/7106082012005-20240215-025147--2065b41b-3ea1-47ef-b2f9-20dd50af7697.jpg","https:\/\/sirekap-obj-formc.kpu.go.id\/053f\/pemilu\/ppwp\/71\/06\/08\/20\/12\/7106082012005-20240215-025305--400e28e4-43a4-49a6-b3b7-191f202a65cf.jpg","https:\/\/sirekap-obj-formc.kpu.go.id\/053f\/pemilu\/ppwp\/71\/06\/08\/20\/12\/7106082012005-20240216-134000--5d61194f-f555-4922-80a4-b38deabe88ed.jpg"],"administrasi":null,"psu":null,"ts":"2024-02-16 14:00:34","status_suara":true,"status_adm":false}},"7106082012006":{"kode_prov":"71","kode_kab":"7106","kode_kec":"710608","kode_kel":"7106082012","kode_tps":"7106082012006","data_tps":{"mode":"hhcw","chart":{"null":null,"100025":9,"100026":156,"100027":11},"images":["https:\/\/sirekap-obj-formc.kpu.go.id\/999f\/pemilu\/ppwp\/71\/06\/08\/20\/12\/7106082012006-20240218-205902--08f2a157-a44e-438b-a133-aebd14bb29e7.jpg","https:\/\/sirekap-obj-formc.kpu.go.id\/999f\/pemilu\/ppwp\/71\/06\/08\/20\/12\/7106082012006-20240218-205947--d32a08bc-b8cd-40c9-b89c-fdc900cd09c6.jpg","https:\/\/sirekap-obj-formc.kpu.go.id\/999f\/pemilu\/ppwp\/71\/06\/08\/20\/12\/7106082012006-20240218-210141--083533e1-8c71-4c03-90f1-bf7fb506f71a.jpg"],"administrasi":{"suara_sah":176,"suara_total":176,"pemilih_dpt_j":221,"pemilih_dpt_l":85,"pemilih_dpt_p":136,"pengguna_dpt_j":161,"pengguna_dpt_l":54,"pengguna_dpt_p":107,"pengguna_dptb_j":6,"pengguna_dptb_l":1,"pengguna_dptb_p":5,"suara_tidak_sah":0,"pengguna_total_j":176,"pengguna_total_l":55,"pengguna_total_p":121,"pengguna_non_dpt_j":9,"pengguna_non_dpt_l":0,"pengguna_non_dpt_p":9},"psu":null,"ts":"2024-02-19 06:16:00","status_suara":true,"status_adm":true}},"7106082012007":{"kode_prov":"71","kode_kab":"7106","kode_kec":"710608","kode_kel":"7106082012","kode_tps":"7106082012007","data_tps":{"chart":{"null":null,"100025":21,"100026":143,"100027":25},"images":["https:\/\/sirekap-obj-formc.kpu.go.id\/05e0\/pemilu\/ppwp\/71\/06\/08\/20\/12\/7106082012007-20240215-083452--38cb0d19-c917-4a51-a9ff-62d033d64308.jpg","https:\/\/sirekap-obj-formc.kpu.go.id\/05e0\/pemilu\/ppwp\/71\/06\/08\/20\/12\/7106082012007-20240215-012859--cf71e258-c35c-49de-beab-da7b79b97009.jpg","https:\/\/sirekap-obj-formc.kpu.go.id\/05e0\/pemilu\/ppwp\/71\/06\/08\/20\/12\/7106082012007-20240215-083856--67adacd7-97f3-4642-8e9c-f25558ed940b.jpg"],"administrasi":{"suara_sah":189,"suara_total":191,"pemilih_dpt_j":236,"pemilih_dpt_l":116,"pemilih_dpt_p":120,"pengguna_dpt_j":189,"pengguna_dpt_l":88,"pengguna_dpt_p":101,"pengguna_dptb_j":1,"pengguna_dptb_l":0,"pengguna_dptb_p":1,"suara_tidak_sah":2,"pengguna_total_j":191,"pengguna_total_l":89,"pengguna_total_p":102,"pengguna_non_dpt_j":1,"pengguna_non_dpt_l":1,"pengguna_non_dpt_p":0},"psu":null,"ts":"2024-02-15 21:01:18","status_suara":true,"status_adm":true}},"7106082012008":{"kode_prov":"71","kode_kab":"7106","kode_kec":"710608","kode_kel":"7106082012","kode_tps":"7106082012008","data_tps":{"chart":{"null":null,"100025":13,"100026":141,"100027":22},"images":["https:\/\/sirekap-obj-formc.kpu.go.id\/3e88\/pemilu\/ppwp\/71\/06\/08\/20\/12\/7106082012008-20240216-000311--73e38efd-5fca-4c4e-820a-0d9374442c1f.jpg","https:\/\/sirekap-obj-formc.kpu.go.id\/3e88\/pemilu\/ppwp\/71\/06\/08\/20\/12\/7106082012008-20240216-000313--6b924c88-3093-4675-8648-07e8abcae302.jpg","https:\/\/sirekap-obj-formc.kpu.go.id\/3e88\/pemilu\/ppwp\/71\/06\/08\/20\/12\/7106082012008-20240216-000312--b0cc9991-20b4-4e4e-a268-62b4ca856d89.jpg"],"administrasi":{"suara_sah":176,"suara_total":177,"pemilih_dpt_j":227,"pemilih_dpt_l":109,"pemilih_dpt_p":118,"pengguna_dpt_j":167,"pengguna_dpt_l":82,"pengguna_dpt_p":85,"pengguna_dptb_j":1,"pengguna_dptb_l":0,"pengguna_dptb_p":1,"suara_tidak_sah":1,"pengguna_total_j":177,"pengguna_total_l":87,"pengguna_total_p":90,"pengguna_non_dpt_j":9,"pengguna_non_dpt_l":5,"pengguna_non_dpt_p":4},"psu":null,"ts":"2024-02-16 00:30:27","status_suara":true,"status_adm":true}}}